<room id="docks3" coreLibs="lib/docks.swf,lib/harbor_fx.swf,lib/mcmanus.swf,lib/shroom.swf" voiceLibs="voice/docks3_voice.swf" enterScript="_enter" exitScript="_exit" grid="main,lighthouse" sound1="lib/harbor_fx.swf:HarborNightMusic" sound2="lib/harbor_fx.swf:HarborNightFx">
  <grids>
    <grid id="main">
      <boxes>
        <box x="371" y="1142" w="59" h="73" nodes="n0,n10,n23,n36" />
        <box x="117" y="888" w="161" h="17" nodes="n22,n30" />
        <box x="51" y="1029" w="173" h="49" nodes="n4,n6,n24" />
        <box x="122" y="896" w="45" h="48" nodes="n30" />
        <box x="77" y="1256" w="329" h="86" nodes="n31,n33,n34" />
        <box x="90" y="1061" w="292" h="211" nodes="n6,n7,n10,n23,n24,n27,n31,n33,n34" />
      </boxes>
      <nodes>
        <node id="n0" x="427" y="1210" join="n10,n23,n36" trap="0" name="game_start" />
        <node id="n4" x="215" y="1033" join="n9,n7,n6,n24" trap="0" />
        <node id="n5" x="395" y="878" join="n18,n8,n19" trap="1" />
        <node id="n6" x="212" y="1071" join="n4,n24,n7,n10,n23,n27,n31,n33,n34" trap="0" />
        <node id="n7" x="275" y="1067" join="n4,n25,n6,n10,n23,n24,n27,n31,n33,n34" trap="0" />
        <node id="n8" x="350" y="895" join="n9,n22,n5" trap="1" />
        <node id="n9" x="265" y="938" join="n8,n22,n4,n25" trap="0" />
        <node id="n10" x="377" y="1149" join="n0,n23,n36,n6,n7,n24,n27,n31,n33,n34" trap="0" />
        <node id="n14" x="372" y="821" join="n19" trap="0" name="join_harbor" />
        <node id="n16" x="489" y="838" join="n18" trap="0" name="join_boathouse" />
        <node id="n18" x="454" y="854" join="n16,n5,n19" trap="1" name="barrel" />
        <node id="n19" x="405" y="840" join="n14,n18,n5" trap="1" name="poster" />
        <node id="n22" x="274" y="896" join="n9,n8,n30" trap="1" />
        <node id="n23" x="377" y="1209" join="n0,n10,n36,n6,n7,n24,n27,n31,n33,n34" trap="0" />
        <node id="n24" x="107" y="1073" join="n4,n6,n7,n10,n23,n27,n31,n33,n34" trap="0" />
        <node id="n25" x="265" y="990" join="n7,n9" trap="0" name="crates" />
        <node id="n27" x="191" y="1197" join="n6,n7,n10,n23,n24,n31,n33,n34" trap="0" name="cainstop" />
        <node id="n30" x="139" y="901" join="n22" trap="0" />
        <node id="n31" x="364" y="1269" join="n33,n34,n6,n7,n10,n23,n24,n27" trap="0" />
        <node id="n33" x="219" y="1263" join="n31,n34,n6,n7,n10,n23,n24,n27" trap="0" />
        <node id="n34" x="99" y="1262" join="n31,n33,n6,n7,n10,n23,n24,n27" trap="0" />
        <node id="n36" x="414" y="1190" join="n0,n10,n23" trap="0" name="mcmanusshroom" />
      </nodes>
    </grid>
    <grid id="lighthouse">
      <boxes />
      <nodes>
        <node id="n0" x="246" y="875" join="n1" trap="0" name="lighthouse_bottom" />
        <node id="n1" x="238" y="812" join="n2,n0" trap="0" />
        <node id="n2" x="190" y="762" join="n1,n3" trap="0" />
        <node id="n3" x="190" y="384" join="n2,n5" trap="0" />
        <node id="n4" x="222" y="332" join="n5,n6" trap="1" name="lamp" />
        <node id="n5" x="180" y="343" join="n3,n4" trap="1" name="lighthouse_top" />
        <node id="n6" x="258" y="343" join="n4" trap="1" name="freefall" />
      </nodes>
    </grid>
  </grids>
  <positions>
    <position id="game_start" turn="4" x="427" y="1210" />
    <position id="join_harbor" turn="4" x="372" y="821" />
    <position id="join_boathouse" turn="6" x="489" y="838" />
    <position id="barrel" turn="4" x="454" y="854" />
    <position id="poster" turn="4" x="405" y="840" />
    <position id="crates" turn="4" x="265" y="990" />
    <position id="cainstop" turn="4" x="191" y="1197" />
    <position id="mcmanusshroom" turn="4" x="414" y="1190" />
    <position id="lighthouse_bottom" turn="4" x="246" y="875" />
    <position id="lamp" turn="4" x="222" y="332" />
    <position id="lighthouse_top" turn="4" x="180" y="343" />
    <position id="freefall" turn="4" x="258" y="343" />
  </positions>
  <filters>
    <filter id="baseScale" axis="y" enabled="1">
      <pole x="364" y="841" scale="0.19" rate="0.2" blur="1" color="0x000000" tint="0.5" />
      <pole x="363" y="1322" scale="0.88" rate="0.15" blur="5" color="0xFFFFFF" tint="0.5" />
    </filter>
    <filter id="cainscale" axis="y" enabled="1">
      <pole x="368" y="817" scale="0.22" rate="0.13" blur="1" color="0x000000" tint="0.5" />
      <pole x="368" y="1200" scale="0.93" rate="0.13" blur="5" color="0xFFFFFF" tint="0.5" />
    </filter>
  </filters>
  <scripts>
    <script id="_enter">
      <curtain blackout="0" />
    </script>
    <script id="_exit">
      <curtain blackout="1" />
    </script>
    <script id="_cleanup">
      <library unloadRoom="_current" />
    </script>
  </scripts>
  <layers>
    <layer id="_bg" type="background" asset="lib/docks.swf:DocksBg" depth="0" visible="1" state="main">
      <states>
        <state id="main" x="0" y="0" img="1" imgX="0" imgY="0" imgW="1" imgH="1" frame="2" blend="normal" alpha="1" bitmap="0" hit="1" hitX="0" hitY="0" hitW="1024" hitH="1417" shape="rect">
          <param mouse="1" scrollL="300" scrollR="300" scrollT="450" scrollB="300" />
          <vars />
          <title>
            <en><![CDATA[]]></en>
            <de><![CDATA[]]></de>
          </title>
          <actions />
          <items />
        </state>
      </states>
    </layer>
    <layer id="sea_doors" type="puppet" asset="lib/docks.swf:DocksSeaDoors" depth="1" visible="1" state="main">
      <states>
        <state id="main" x="648" y="904" img="1" imgX="-3" imgY="-196" imgW="1" imgH="1" frame="2" blend="normal" alpha="1" bitmap="1" hit="1" hitX="-6" hitY="-198" hitW="86" hitH="173" shape="rect">
          <param mapX="470" mapY="855" turnTo="5" turn="0" cursor="" onclick="-1" prefix="" subtitle="0xFFFFFF" mouse="1" float="0" tween="7" rotate="0" scroller="0" scale="" color="" rate="" blur="" />
          <vars />
          <title>
            <en><![CDATA[sea doors]]></en>
            <de><![CDATA[Türen zum Meer]]></de>
          </title>
          <actions>
            <action id="act0">
              <title>
                <en><![CDATA[Look at]]></en>
                <de><![CDATA[Untersuche]]></de>
              </title>
              <dialog>
                <dia puppet="_avatar" frame="" sound="voice/docks3_voice.swf:docks30000">
                  <en><![CDATA[A boathouse room with a view.]]></en>
                  <de><![CDATA[Ein Bootshauszimmer mit Aussicht.]]></de>
                </dia>
              </dialog>
              <script>
                <dialogue play="*" />
              </script>
            </action>
            <action id="act1">
              <title>
                <en><![CDATA[Talk to]]></en>
                <de><![CDATA[Sprich mit]]></de>
              </title>
              <dialog />
              <script>
                <dialogue play="*" />
              </script>
            </action>
            <action id="act2">
              <title>
                <en><![CDATA[Use]]></en>
                <de><![CDATA[Benutze]]></de>
              </title>
              <dialog>
                <dia puppet="_avatar" frame="" sound="voice/docks3_voice.swf:docks30001">
                  <en><![CDATA[I’d better just use the human access door.]]></en>
                  <de><![CDATA[Ich nehme besser einfach die Zugangstür für Menschen.]]></de>
                </dia>
              </dialog>
              <script />
            </action>
          </actions>
          <items />
        </state>
      </states>
    </layer>
    <layer id="water" type="plane" asset="lib/docks.swf:DocksWater" depth="2" visible="1" state="main">
      <states>
        <state id="main" x="403" y="829" img="1" imgX="0" imgY="0" imgW="1" imgH="1" frame="2" blend="normal" alpha="1" bitmap="0" hit="0" hitX="0" hitY="0" hitW="100" hitH="100" shape="rect">
          <param mouse="0" float="0" parallax="" />
          <vars />
          <title>
            <en><![CDATA[]]></en>
            <de><![CDATA[]]></de>
          </title>
          <actions />
          <items />
        </state>
      </states>
    </layer>
    <layer id="lighthouse_door" type="puppet" asset="lib/docks.swf:DocksLighthouseDoor" depth="3" visible="1" state="closed">
      <states>
        <state id="closed" x="250" y="870" img="1" imgX="-26" imgY="-113" imgW="1" imgH="1" frame="2" blend="normal" alpha="1" bitmap="0" hit="1" hitX="-26" hitY="-113" hitW="48" hitH="126" shape="rect">
          <param mapX="265" mapY="890" turnTo="5" turn="0" cursor="" onclick="-1" prefix="" subtitle="0xFFFFFF" mouse="1" float="0" tween="7" rotate="0" scroller="0" scale="" color="" rate="" blur="" />
          <vars />
          <title>
            <en><![CDATA[lighthouse door]]></en>
            <de><![CDATA[Leuchtturmtür]]></de>
          </title>
          <actions>
            <action id="act0">
              <title>
                <en><![CDATA[Look at]]></en>
                <de><![CDATA[Untersuche]]></de>
              </title>
              <dialog>
                <dia puppet="_avatar" frame="" sound="voice/docks3_voice.swf:docks30002">
                  <en><![CDATA[This door leads into the lighthouse.]]></en>
                  <de><![CDATA[Diese Tür führt in den Leuchtturm.]]></de>
                </dia>
              </dialog>
              <script>
                <dialogue play="*" />
              </script>
            </action>
            <action id="act1">
              <title>
                <en><![CDATA[Talk to]]></en>
                <de><![CDATA[Sprich mit]]></de>
              </title>
              <dialog>
                <dia puppet="_avatar" frame="" sound="voice/docks3_voice.swf:docks30003">
                  <en><![CDATA[Is anyone in there?]]></en>
                  <de><![CDATA[Ist jemand hier drin?]]></de>
                </dia>
                <dia puppet="_avatar" frame="" sound="voice/docks3_voice.swf:docks30004">
                  <en><![CDATA[Hello?]]></en>
                  <de><![CDATA[Hallo?]]></de>
                </dia>
                <dia puppet="_avatar" frame="lspeak5" sound="voice/docks3_voice.swf:docks30005">
                  <en><![CDATA[I don’t think there’s anyone inside the lighthouse.]]></en>
                  <de><![CDATA[Ich glaube nicht, dass im Leuchtturm jemand ist.]]></de>
                </dia>
              </dialog>
              <script>
                <dialogue play="*" />
              </script>
            </action>
            <action id="act2">
              <title>
                <en><![CDATA[Open]]></en>
                <de><![CDATA[Öffne]]></de>
              </title>
              <dialog>
                <dia puppet="_avatar" frame="" sound="voice/docks3_voice.swf:docks30006">
                  <en><![CDATA[The lighthouse door is locked. What a surprise.]]></en>
                  <de><![CDATA[Die Tür zum Leuchtturm ist verschlossen. Wie überraschend.]]></de>
                </dia>
              </dialog>
              <script>
                <dialogue play="*" />
              </script>
            </action>
          </actions>
          <items>
            <action id="lighthouse_key">
              <title>
                <en><![CDATA[]]></en>
              </title>
              <dialog>
                <dia puppet="_avatar" frame="hspeak" sound="voice/docks3_voice.swf:docks30007">
                  <en><![CDATA[I’m in!]]></en>
                  <de><![CDATA[Ich bin drin!]]></de>
                </dia>
              </dialog>
              <script>
                <method call="controls" enabled="0" />
                <layerSprite target="_avatar" animFrame="reach_out" waitForComplete="1" />
                <layer target="_current:lighthouse_door" state="open" />
                <layer target="_current:lighthouse_tower" visible="1" />
                <sound effect="lib/sound_effects.swf:doorLock" waitForComplete="0" />
                <layerSprite target="_avatar" animFrame="reach_in" waitForComplete="1" />
                <method call="controls" enabled="1" />
                <dialogue play="*" />
              </script>
            </action>
          </items>
        </state>
        <state id="open" x="250" y="870" img="0" imgX="-26" imgY="-113" imgW="1" imgH="1" frame="2" blend="normal" alpha="1" bitmap="0" hit="1" hitX="-26" hitY="-113" hitW="43" hitH="121" shape="rect">
          <param mapX="265" mapY="890" turnTo="5" turn="0" cursor="exit1" onclick="0" prefix="" subtitle="0xFFFFFF" mouse="1" float="0" tween="7" rotate="0" scroller="0" scale="" color="" rate="" blur="" />
          <vars />
          <title>
            <en><![CDATA[lighthouse door]]></en>
            <de><![CDATA[Leuchtturmtür]]></de>
          </title>
          <actions>
            <action id="act0">
              <title>
                <en><![CDATA[Look at]]></en>
                <de><![CDATA[Untersuche]]></de>
              </title>
              <dialog />
              <script>
                <method call="controls" enabled="0" />
                <room target="_current" grid="lighthouse" />
                <puppetTween target="_avatar" type="move" to="position:lighthouse_top" waitForComplete="1" />
                <layerState target="_current:lighthouse_tower:main" mouseEnabled="1" />
                <layerState target="_current:lighthouse_oil:main" mouseEnabled="1" />
                <layerState target="_current:windmill:main" mouseEnabled="1" />
                <layer target="_current:exit_ground1" visible="1" />
                <layer target="_current:exit_ground2" visible="1" />
                <method call="controls" enabled="1" />
              </script>
            </action>
            <action id="act1">
              <title>
                <en><![CDATA[Talk to]]></en>
                <de><![CDATA[Sprich mit]]></de>
              </title>
              <dialog />
              <script>
                <dialogue play="*" />
              </script>
            </action>
            <action id="act2">
              <title>
                <en><![CDATA[Use]]></en>
                <de><![CDATA[Benutze]]></de>
              </title>
              <dialog />
              <script>
                <dialogue play="*" />
              </script>
            </action>
          </actions>
          <items />
        </state>
      </states>
    </layer>
    <layer id="sky" type="puppet" asset="" depth="4" visible="1" state="main">
      <states>
        <state id="main" x="849" y="344" img="1" imgX="0" imgY="0" imgW="1" imgH="1" frame="1" blend="normal" alpha="1" bitmap="0" hit="1" hitX="-549" hitY="-465" hitW="728" hitH="505" shape="rect">
          <param mapX="222" mapY="332" turnTo="5" turn="0" cursor="" onclick="-1" prefix="" subtitle="0xFFFFFF" mouse="1" float="0" tween="7" rotate="0" scroller="0" scale="" color="" rate="" blur="" />
          <vars />
          <title>
            <en><![CDATA[starry starry night]]></en>
            <de><![CDATA[sternenklare Nacht]]></de>
          </title>
          <actions>
            <action id="act0">
              <title>
                <en><![CDATA[Look at]]></en>
                <de><![CDATA[Untersuche]]></de>
              </title>
              <dialog>
                <dia puppet="_avatar" frame="" sound="voice/docks3_voice.swf:docks30008">
                  <en><![CDATA[What a beautiful night.]]></en>
                  <de><![CDATA[Was für eine wundervolle Nacht.]]></de>
                </dia>
              </dialog>
              <script>
                <dialogue play="*" />
              </script>
            </action>
            <action id="act1">
              <title>
                <en><![CDATA[Talk to]]></en>
                <de><![CDATA[Sprich mit]]></de>
              </title>
              <dialog />
              <script>
                <dialogue play="*" />
              </script>
            </action>
            <action id="act2">
              <title>
                <en><![CDATA[Use]]></en>
                <de><![CDATA[Benutze]]></de>
              </title>
              <dialog />
              <script>
                <dialogue play="*" />
              </script>
            </action>
          </actions>
          <items />
        </state>
      </states>
    </layer>
    <layer id="lighthouse_lamp" type="puppet" asset="lib/docks.swf:DocksLighthouseTop" depth="5" visible="1" state="main">
      <states>
        <state id="main" x="223" y="326" img="1" imgX="-51" imgY="-142" imgW="1" imgH="1" frame="1" blend="normal" alpha="1" bitmap="0" hit="1" hitX="-40" hitY="-140" hitW="74" hitH="95" shape="rect">
          <param mapX="222" mapY="332" turnTo="5" turn="0" cursor="" onclick="-1" prefix="" subtitle="0xFFFFFF" mouse="1" float="0" tween="7" rotate="0" scroller="0" scale="" color="" rate="" blur="" />
          <vars />
          <title>
            <en><![CDATA[lighthouse lamp]]></en>
            <de><![CDATA[Leuchtturmlampe]]></de>
          </title>
          <actions>
            <action id="act0">
              <title>
                <en><![CDATA[Look at]]></en>
                <de><![CDATA[Untersuche]]></de>
              </title>
              <dialog>
                <dia puppet="_avatar" frame="" sound="voice/docks3_voice.swf:docks30009">
                  <en><![CDATA[That is quite possibly the biggest oil lamp that I’ve ever seen!]]></en>
                  <de><![CDATA[Das ist wahrscheinlich die größte Öllampe, die ich je gesehen habe!]]></de>
                </dia>
                <dia puppet="_avatar" frame="" sound="voice/docks3_voice.swf:docks30010">
                  <en><![CDATA[There’s an oil funnel at the base of the lamp. Apparently the lighthouse keeper needs to refill the oil each night.]]></en>
                  <de><![CDATA[Unten an der Lampe ist ein Öltrichter. Offenbar muss der Leuchtturmwärter jeden Abend Öl nachfüllen.]]></de>
                </dia>
              </dialog>
              <script>
                <dialogue play="*" />
              </script>
            </action>
            <action id="act1">
              <title>
                <en><![CDATA[Talk to]]></en>
                <de><![CDATA[Sprich mit]]></de>
              </title>
              <dialog />
              <script>
                <dialogue play="*" />
              </script>
            </action>
            <action id="act2">
              <title>
                <en><![CDATA[Wave at]]></en>
                <de><![CDATA[Winke]]></de>
              </title>
              <dialog>
                <dia puppet="_avatar" frame="" sound="voice/docks3_voice.swf:docks30011">
                  <en><![CDATA[Wow, I can make some serious shadow puppets in the light!]]></en>
                  <de><![CDATA[Wow, in diesem Licht kann ich richtig tolle Schattenfiguren machen!]]></de>
                </dia>
              </dialog>
              <script>
                <dialogue play="*" />
              </script>
            </action>
          </actions>
          <items>
            <action id="torches">
              <title>
                <en><![CDATA[Dip #item# into #noun#]]></en>
                <de><![CDATA[Tauche #item# in #noun#]]></de>
              </title>
              <dialog />
              <script>
                <params walkTo="none" />
                <dialogue play="none" />
                <puppet target="lighthouse_oil" callItemAction="torches" />
              </script>
            </action>
          </items>
        </state>
      </states>
    </layer>
    <layer id="exit_ground2" type="puppet" asset="" depth="6" visible="1" state="main">
      <states>
        <state id="main" x="155" y="335" img="1" imgX="0" imgY="0" imgW="1" imgH="1" frame="1" blend="normal" alpha="1" bitmap="0" hit="1" hitX="-40" hitY="-130" hitW="80" hitH="135" shape="rect">
          <param mapX="180" mapY="343" turnTo="5" turn="0" cursor="exit4" onclick="0" prefix="" subtitle="0xFFFFFF" mouse="1" float="0" tween="7" rotate="0" scroller="0" scale="" color="" rate="" blur="" />
          <vars />
          <title>
            <en><![CDATA[]]></en>
            <de><![CDATA[]]></de>
          </title>
          <actions>
            <action id="act0">
              <title>
                <en><![CDATA[Look at]]></en>
                <de><![CDATA[Untersuche]]></de>
              </title>
              <dialog />
              <script>
                <puppet target="exit_ground1" callAction="0" />
              </script>
            </action>
            <action id="act1">
              <title>
                <en><![CDATA[Talk to]]></en>
                <de><![CDATA[Sprich mit]]></de>
              </title>
              <dialog />
              <script>
                <dialogue play="*" />
              </script>
            </action>
            <action id="act2">
              <title>
                <en><![CDATA[Use]]></en>
                <de><![CDATA[Benutze]]></de>
              </title>
              <dialog />
              <script>
                <dialogue play="*" />
              </script>
            </action>
          </actions>
          <items />
        </state>
      </states>
    </layer>
    <layer id="boat" type="puppet" asset="lib/docks.swf:DocksBoat" depth="7" visible="1" state="main">
      <states>
        <state id="main" x="526" y="1160" img="1" imgX="-87" imgY="-238" imgW="1" imgH="1" frame="1" blend="normal" alpha="1" bitmap="0" hit="1" hitX="-65" hitY="-266" hitW="580" hitH="250" shape="rect">
          <param mapX="414" mapY="1190" turnTo="5" turn="0" cursor="" onclick="-1" prefix="" subtitle="0xFFFFFF" mouse="1" float="0" tween="7" rotate="0" scroller="0" scale="" color="" rate="" blur="" />
          <vars />
          <title>
            <en><![CDATA[boat]]></en>
            <de><![CDATA[Boot]]></de>
          </title>
          <actions>
            <action id="act0">
              <title>
                <en><![CDATA[Look at]]></en>
                <de><![CDATA[Untersuche]]></de>
              </title>
              <dialog>
                <dia puppet="_avatar" frame="" sound="voice/docks3_voice.swf:docks30012">
                  <en><![CDATA[That’s McManus’ boat ... Vincent left it here after he kidnapped Nora.]]></en>
                  <de><![CDATA[Das ist das Boot von McManus ... Vincent hat es hier zurückgelassen, nachdem er Nora entführt hat.]]></de>
                </dia>
              </dialog>
              <script>
                <dialogue play="*" />
              </script>
            </action>
            <action id="act1">
              <title>
                <en><![CDATA[Talk to]]></en>
                <de><![CDATA[Sprich mit]]></de>
              </title>
              <dialog />
              <script>
                <dialogue play="*" />
              </script>
            </action>
            <action id="act2">
              <title>
                <en><![CDATA[Use]]></en>
                <de><![CDATA[Benutze]]></de>
              </title>
              <dialog>
                <dia puppet="_avatar" frame="" sound="voice/docks3_voice.swf:docks30013">
                  <en><![CDATA[No, I think this tired old boat is dead in the water... literally.]]></en>
                  <de><![CDATA[Nein, ich glaube, dieses müde alte Boot ist ein Wrack ... und ich meine nicht nervlich.]]></de>
                </dia>
              </dialog>
              <script>
                <dialogue play="*" />
              </script>
            </action>
          </actions>
          <items />
        </state>
      </states>
    </layer>
    <layer id="lighthouse_oil" type="puppet" asset="lib/docks.swf:DocksOilDrip" depth="8" visible="1" state="main">
      <states>
        <state id="main" x="252" y="341" img="1" imgX="-4" imgY="-54" imgW="1" imgH="1" frame="1" blend="normal" alpha="1" bitmap="0" hit="1" hitX="-19" hitY="-87" hitW="44" hitH="46" shape="rect">
          <param mapX="222" mapY="332" turnTo="5" turn="0" cursor="" onclick="-1" prefix="" subtitle="0xFFFFFF" mouse="0" float="0" tween="7" rotate="0" scroller="0" scale="" color="" rate="" blur="" />
          <vars />
          <title>
            <en><![CDATA[oil funnel]]></en>
            <de><![CDATA[Öltrichter]]></de>
          </title>
          <actions>
            <action id="act0">
              <title>
                <en><![CDATA[Look at]]></en>
                <de><![CDATA[Untersuche]]></de>
              </title>
              <dialog>
                <dia puppet="_avatar" frame="" sound="voice/docks3_voice.swf:docks30014">
                  <en><![CDATA[It’s a large open nozzle used to refill the lamp’s oil reserve.]]></en>
                  <de><![CDATA[Das ist ein großer, offener Stutzen, mit dem man den Ölbehälter der Lampe auffüllt. ]]></de>
                </dia>
                <dia puppet="_avatar" frame="" sound="voice/docks3_voice.swf:docks30015">
                  <en><![CDATA[Judging by the strong smell of oil and the intensity of the lamp light, I’d guess that the oil reserve is still mostly full.]]></en>
                  <de><![CDATA[Dem starken Ölgeruch und der Intensität des Lampenlichts nach zu urteilen würde ich schätzen, dass der Ölbehälter noch fast voll ist.]]></de>
                </dia>
              </dialog>
              <script>
                <dialogue play="*" />
              </script>
            </action>
            <action id="act1">
              <title>
                <en><![CDATA[Talk to]]></en>
                <de><![CDATA[Sprich mit]]></de>
              </title>
              <dialog />
              <script>
                <dialogue play="*" />
              </script>
            </action>
            <action id="act2">
              <title>
                <en><![CDATA[Extract oil from]]></en>
                <de><![CDATA[Hole Öl aus]]></de>
              </title>
              <dialog>
                <dia puppet="_avatar" frame="" sound="voice/docks3_voice.swf:docks30016">
                  <en><![CDATA[I’ll need to insert something into the funnel to soak up some oil.]]></en>
                  <de><![CDATA[Ich muss etwas in den Trichter stecken, um etwas Öl aufzusaugen.]]></de>
                </dia>
              </dialog>
              <script>
                <dialogue play="*" />
              </script>
            </action>
          </actions>
          <items>
            <action id="torches">
              <title>
                <en><![CDATA[Dip #item# into #noun#]]></en>
                <de><![CDATA[Tauche #item# in #noun#]]></de>
              </title>
              <dialog>
                <dia puppet="_avatar" frame="" sound="voice/docks3_voice.swf:docks30017">
                  <en><![CDATA[Perfect, the torches fit down the funnel and into the lamp’s oil reserve.]]></en>
                  <de><![CDATA[Perfekt, die Fackel passt durch den Trichter und in den Ölbehälter der Lampe.]]></de>
                </dia>
                <dia puppet="_avatar" frame="" sound="voice/docks3_voice.swf:docks30018">
                  <en><![CDATA[The torch wicks are soaked with oil now.]]></en>
                  <de><![CDATA[Die Dochte der Fackel sind jetzt mit Öl getränkt.]]></de>
                </dia>
              </dialog>
              <script>
                <method call="controls" enabled="0" />
                <layerSprite target="_avatar" animFrame="reach_out" waitForComplete="1" />
                <inventory replace="torches:torches_oil" />
                <layerSprite target="_avatar" animFrame="reach_in" waitForComplete="1" />
                <method call="controls" enabled="1" />
                <dialogue play="*" />
              </script>
            </action>
            <action id="torches_fire">
              <title>
                <en><![CDATA[Dip #item# into #noun#]]></en>
                <de><![CDATA[Tauche #item# in #noun#]]></de>
              </title>
              <dialog>
                <dia puppet="_avatar" frame="" sound="voice/docks3_voice.swf:docks30019">
                  <en><![CDATA[That would be a very ugly end for my adventure.]]></en>
                  <de><![CDATA[Das wäre ein sehr hässliches Ende für mein Abenteuer.]]></de>
                </dia>
              </dialog>
              <script>
                <dialogue play="*" />
              </script>
            </action>
          </items>
        </state>
      </states>
    </layer>
    <layer id="windmill" type="puppet" asset="lib/docks.swf:DocksWindmill" depth="9" visible="1" state="main">
      <states>
        <state id="main" x="637" y="428" img="1" imgX="-27" imgY="-25" imgW="1" imgH="1" frame="2" blend="normal" alpha="1" bitmap="0" hit="1" hitX="-40" hitY="-39" hitW="79" hitH="97" shape="rect">
          <param mapX="258" mapY="343" turnTo="5" turn="0" cursor="" onclick="-1" prefix="" subtitle="0xFFFFFF" mouse="0" float="0" tween="7" rotate="0" scroller="0" scale="" color="" rate="" blur="" />
          <vars />
          <title>
            <en><![CDATA[windmill]]></en>
            <de><![CDATA[Windmühle]]></de>
          </title>
          <actions>
            <action id="act0">
              <title>
                <en><![CDATA[Look at]]></en>
                <de><![CDATA[Untersuche]]></de>
              </title>
              <dialog />
              <script>
                <dialogue play="*" />
              </script>
            </action>
            <action id="act1">
              <title>
                <en><![CDATA[Talk to]]></en>
                <de><![CDATA[Sprich mit]]></de>
              </title>
              <dialog />
              <script>
                <dialogue play="*" />
              </script>
            </action>
            <action id="act2">
              <title>
                <en><![CDATA[Use]]></en>
                <de><![CDATA[Benutze]]></de>
              </title>
              <dialog />
              <script>
                <dialogue play="*" />
              </script>
            </action>
          </actions>
          <items />
        </state>
      </states>
    </layer>
    <layer id="arch" type="puppet" asset="lib/docks.swf:DocksArch" depth="10" visible="1" state="main">
      <states>
        <state id="main" x="355" y="846" img="1" imgX="-85" imgY="-214" imgW="1" imgH="1" frame="2" blend="normal" alpha="1" bitmap="1" hit="1" hitX="-30" hitY="-124" hitW="89" hitH="115" shape="rect">
          <param mapX="315" mapY="815" turnTo="5" turn="0" cursor="exit7" onclick="0" prefix="" subtitle="0xFFFFFF" mouse="1" float="1" tween="1" rotate="0" scroller="0" scale="" color="" rate="" blur="" />
          <vars />
          <title>
            <en><![CDATA[]]></en>
            <de><![CDATA[]]></de>
          </title>
          <actions>
            <action id="act0">
              <title>
                <en><![CDATA[Look at]]></en>
                <de><![CDATA[Untersuche]]></de>
              </title>
              <dialog />
              <script>
                <game room="harbor3:join_docks" />
              </script>
            </action>
            <action id="act1">
              <title>
                <en><![CDATA[Talk to]]></en>
                <de><![CDATA[Sprich mit]]></de>
              </title>
              <dialog />
              <script>
                <dialogue play="*" />
              </script>
            </action>
            <action id="act2">
              <title>
                <en><![CDATA[Use]]></en>
                <de><![CDATA[Benutze]]></de>
              </title>
              <dialog />
              <script>
                <dialogue play="*" />
              </script>
            </action>
          </actions>
          <items />
        </state>
      </states>
    </layer>
    <layer id="lighthouse_tower" type="puppet" asset="lib/docks.swf:DocksLighthouseTower" depth="11" visible="0" state="main">
      <states>
        <state id="main" x="263" y="866" img="1" imgX="-135" imgY="-590" imgW="1" imgH="1" frame="1" blend="normal" alpha="1" bitmap="0" hit="1" hitX="-115" hitY="-526" hitW="399" hitH="322" shape="rect">
          <param mapX="258" mapY="343" turnTo="5" turn="0" cursor="" onclick="-1" prefix="" subtitle="0xFFFFFF" mouse="0" float="1" tween="7" rotate="0" scroller="0" scale="" color="" rate="" blur="" />
          <vars />
          <title>
            <en><![CDATA[tower freefall]]></en>
            <de><![CDATA[freier Fall vom Turm]]></de>
          </title>
          <actions>
            <action id="act0">
              <title>
                <en><![CDATA[Look at]]></en>
                <de><![CDATA[Untersuche]]></de>
              </title>
              <dialog>
                <dia puppet="_avatar" frame="" sound="voice/docks3_voice.swf:docks30020">
                  <en><![CDATA[Wow, it’s a long way down... why do towers always seem so much taller from the top than from the ground?]]></en>
                  <de><![CDATA[Wow, da geht es tief runter ... Warum wirken Türme von oben immer viel höher als vom Boden aus?]]></de>
                </dia>
              </dialog>
              <script>
                <dialogue play="*" />
              </script>
            </action>
            <action id="act1">
              <title>
                <en><![CDATA[Talk to]]></en>
                <de><![CDATA[Sprich mit]]></de>
              </title>
              <dialog />
              <script>
                <dialogue play="*" />
              </script>
            </action>
            <action id="act2">
              <title>
                <en><![CDATA[Jump from]]></en>
                <de><![CDATA[Spring von]]></de>
              </title>
              <dialog>
                <dia puppet="_avatar" frame="" sound="voice/docks3_voice.swf:docks30021">
                  <en><![CDATA[Ah, no... jumping is NOT a viable option for the Vincent situation.]]></en>
                  <de><![CDATA[Äh, nein ... springen ist KEINE Alternative für das Vincent-Problem.]]></de>
                </dia>
              </dialog>
              <script>
                <dialogue play="*" />
              </script>
            </action>
          </actions>
          <items>
            <action id="chest_loot">
              <title>
                <en><![CDATA[Throw #item# into #noun#]]></en>
                <de><![CDATA[Wirf #item# in #noun#]]></de>
              </title>
              <dialog>
                <dia puppet="_avatar" frame="" sound="voice/docks3_voice.swf:docks30022">
                  <en><![CDATA[Look out below!]]></en>
                  <de><![CDATA[Vorsicht da unten!]]></de>
                </dia>
                <dia puppet="_avatar" frame="hspeak" sound="voice/docks3_voice.swf:docks30023">
                  <en><![CDATA[Haha! That crate smashed like an egg on the ground below...]]></en>
                  <de><![CDATA[Haha! Diese Kiste ist unten am Boden zerschellt wie ein Ei ...]]></de>
                </dia>
                <dia puppet="_avatar" frame="" sound="voice/docks3_voice.swf:docks30024">
                  <en><![CDATA[Alas feeble strongbox, you were no match for gravity.]]></en>
                  <de><![CDATA[Ach weh, schwache Holzkiste, du warst der Schwerkraft nicht gewachsen.]]></de>
                </dia>
              </dialog>
              <script>
                <dialogue playList="0" />
                <method call="controls" enabled="0" />
                <puppetTween target="_avatar" type="turn" to="view:4" waitForComplete="1" />
                <layerSprite target="_avatar" animFrame="reach_out" waitForComplete="1" />
                <layer target="_current:chest_smash" visible="1" />
                <inventory remove="chest_loot" />
                <layerSprite target="chest_smash" animFrame="throw" waitForComplete="1" />
                <layerSprite target="chest_smash" animFrame="ground" waitForComplete="0" />
                <layerSprite target="_avatar" animFrame="reach_in" waitForComplete="1" />
                <method call="controls" enabled="1" />
                <dialogue playList="1,2" />
              </script>
            </action>
          </items>
        </state>
      </states>
    </layer>
    <layer id="sticker" type="puppet" asset="lib/docks.swf:DocksSticker" depth="12" visible="1" state="main">
      <states>
        <state id="main" x="246" y="352" img="1" imgX="-5" imgY="-23" imgW="0.9" imgH="0.9" frame="1" blend="normal" alpha="1" bitmap="0" hit="1" hitX="-16" hitY="-32" hitW="41" hitH="36" shape="rect">
          <param mapX="222" mapY="332" turnTo="5" turn="0" cursor="" onclick="-1" prefix="" subtitle="0xFFFFFF" mouse="1" float="0" tween="7" rotate="0" scroller="0" scale="" color="" rate="" blur="" />
          <vars />
          <title>
            <en><![CDATA[castle sticker]]></en>
            <de><![CDATA[Schloss-Aufkleber]]></de>
          </title>
          <actions>
            <action id="act0">
              <title>
                <en><![CDATA[Look at]]></en>
                <de><![CDATA[Untersuche]]></de>
              </title>
              <dialog>
                <dia puppet="_avatar" frame="" sound="voice/docks3_voice.swf:docks30025">
                  <en><![CDATA[Good grief, those castle goons really did manage to put castle propaganda everywhere...]]></en>
                  <de><![CDATA[Gute Güte, die Beamten vom Schloss haben ihre Propaganda wirklich überall angebracht ...]]></de>
                </dia>
                <dia puppet="_avatar" frame="" sound="voice/docks3_voice.swf:docks30026">
                  <en><![CDATA[I can only assume that this eye looming over the harbor was meant to be symbolic.]]></en>
                  <de><![CDATA[Ich kann nur annehmen, dass dieses Auge, das über dem Hafen schwebt, symbolisch gemeint ist.]]></de>
                </dia>
              </dialog>
              <script>
                <dialogue play="*" />
              </script>
            </action>
            <action id="act1">
              <title>
                <en><![CDATA[Talk to]]></en>
                <de><![CDATA[Sprich mit]]></de>
              </title>
              <dialog />
              <script>
                <dialogue play="*" />
              </script>
            </action>
            <action id="act2">
              <title>
                <en><![CDATA[Peel]]></en>
                <de><![CDATA[Entferne]]></de>
              </title>
              <dialog>
                <dia puppet="_avatar" frame="" sound="voice/docks3_voice.swf:docks30027">
                  <en><![CDATA[The Ravenhollow harbor should be free of this watchful eye.]]></en>
                  <de><![CDATA[Der Hafen von Ravenhollow sollte frei von diesem wachsamen Auge sein.]]></de>
                </dia>
              </dialog>
              <script>
                <method call="controls" enabled="0" />
                <layerSprite target="_avatar" animFrame="kneel_out" waitForComplete="1" />
                <layer target="_current:sticker" visible="0" omit="1" />
                <inventory add="sticker" />
                <layerSprite target="_avatar" animFrame="kneel_in" waitForComplete="1" />
                <method call="controls" enabled="1" />
                <dialogue play="*" />
              </script>
            </action>
          </actions>
          <items />
        </state>
      </states>
    </layer>
    <layer id="chest_smash" type="puppet" asset="lib/docks.swf:DocksBoxThrow" depth="13" visible="0" state="loot">
      <states>
        <state id="loot" x="301" y="900" img="1" imgX="-18" imgY="-604" imgW="1" imgH="1" frame="3" blend="normal" alpha="1" bitmap="0" hit="1" hitX="-29" hitY="-54" hitW="63" hitH="44" shape="rect">
          <param mapX="275" mapY="895" turnTo="5" turn="0" cursor="" onclick="-1" prefix="" subtitle="0xFFFFFF" mouse="1" float="0" tween="7" rotate="0" scroller="0" scale="" color="" rate="" blur="" />
          <vars />
          <title>
            <en><![CDATA[smashed box ’o loot]]></en>
            <de><![CDATA[zerbrochene Kiste mit Zeug]]></de>
          </title>
          <actions>
            <action id="act0">
              <title>
                <en><![CDATA[Look at]]></en>
                <de><![CDATA[Untersuche]]></de>
              </title>
              <dialog>
                <dia puppet="_avatar" frame="" sound="voice/docks3_voice.swf:docks30028">
                  <en><![CDATA[Wow, look at all the loot that was in that box.]]></en>
                  <de><![CDATA[Wow, was in dieser Kiste alles für Zeug drin war.]]></de>
                </dia>
              </dialog>
              <script>
                <dialogue play="*" />
              </script>
            </action>
            <action id="act1">
              <title>
                <en><![CDATA[Talk to]]></en>
                <de><![CDATA[Sprich mit]]></de>
              </title>
              <dialog />
              <script>
                <dialogue play="*" />
              </script>
            </action>
            <action id="act2">
              <title>
                <en><![CDATA[Pick up]]></en>
                <de><![CDATA[Nimm]]></de>
              </title>
              <dialog>
                <dia puppet="_avatar" frame="" sound="voice/docks3_voice.swf:docks30029">
                  <en><![CDATA[Wow! Just look at all this stuff!]]></en>
                  <de><![CDATA[Wow! So viele Sachen!]]></de>
                </dia>
                <dia puppet="_avatar" frame="" sound="voice/docks3_voice.swf:docks30030">
                  <en><![CDATA[These things all look pretty valuable!]]></en>
                  <de><![CDATA[Diese Dinge sehen alle recht wertvoll aus!]]></de>
                </dia>
                <dia puppet="_avatar" frame="" sound="voice/docks3_voice.swf:docks30031">
                  <en><![CDATA[Wait a minute ...  oh no.]]></en>
                  <de><![CDATA[Moment ... Oh nein.]]></de>
                </dia>
                <dia puppet="_avatar" frame="" sound="voice/docks3_voice.swf:docks30032">
                  <en><![CDATA[I think I’m going to be sick ... I shouldn’t have dropped that box from the lighthouse.]]></en>
                  <de><![CDATA[Ich glaube, mir wird schlecht ... Ich hätte die Kiste nicht vom Leuchtturm werfen sollen.]]></de>
                </dia>
              </dialog>
              <script>
                <method call="controls" enabled="0" />
                <dialogue playList="0,1" />
                <layerSprite target="_avatar" animFrame="kneel_out" waitForComplete="1" />
                <layer target="_current:chest_smash" state="empty" />
                <inventory add="treasure1,treasure2,treasure3,dice" />
                <layerSprite target="_avatar" animFrame="kneel_in" waitForComplete="1" />
                <dialogue playList="2,3" />
                <method call="controls" enabled="1" />
              </script>
            </action>
          </actions>
          <items />
        </state>
        <state id="empty" x="301" y="900" img="1" imgX="-18" imgY="-604" imgW="1" imgH="1" frame="4" blend="normal" alpha="1" bitmap="0" hit="1" hitX="-29" hitY="-54" hitW="63" hitH="44" shape="rect">
          <param mapX="275" mapY="895" turnTo="5" turn="0" cursor="" onclick="-1" prefix="" subtitle="0xFFFFFF" mouse="1" float="0" tween="7" rotate="0" scroller="0" scale="" color="" rate="" blur="" />
          <vars />
          <title>
            <en><![CDATA[smashed box]]></en>
            <de><![CDATA[zerbrochene Kiste]]></de>
          </title>
          <actions>
            <action id="act0">
              <title>
                <en><![CDATA[Look at]]></en>
                <de><![CDATA[Untersuche]]></de>
              </title>
              <dialog>
                <dia puppet="_avatar" frame="" sound="voice/docks3_voice.swf:docks30033">
                  <en><![CDATA[It’s the smashed remains of that chest I threw from the top of the lighthouse.]]></en>
                  <de><![CDATA[Das sind die zerbrochenen Überreste der Kiste, die ich vom Leuchtturm heruntergeworfen habe.]]></de>
                </dia>
              </dialog>
              <script>
                <dialogue play="*" />
              </script>
            </action>
            <action id="act1">
              <title>
                <en><![CDATA[Talk to]]></en>
                <de><![CDATA[Sprich mit]]></de>
              </title>
              <dialog />
              <script>
                <dialogue play="*" />
              </script>
            </action>
            <action id="act2">
              <title>
                <en><![CDATA[Pick up]]></en>
                <de><![CDATA[Nimm]]></de>
              </title>
              <dialog>
                <dia puppet="_avatar" frame="" sound="voice/docks3_voice.swf:docks30034">
                  <en><![CDATA[No, I’ve picked the bones. I don’t need the carcass.]]></en>
                  <de><![CDATA[Nein, ich habe mir das Wichtigste rausgepickt. Den Kadaver brauche ich nicht.]]></de>
                </dia>
              </dialog>
              <script>
                <dialogue play="*" />
              </script>
            </action>
          </actions>
          <items />
        </state>
      </states>
    </layer>
    <layer id="back_crates" type="puppet" asset="" depth="14" visible="1" state="main">
      <states>
        <state id="main" x="320" y="858" img="1" imgX="0" imgY="0" imgW="1" imgH="1" frame="1" blend="normal" alpha="1" bitmap="0" hit="1" hitX="-45" hitY="-70" hitW="72" hitH="66" shape="rect">
          <param mapX="377" mapY="873" turnTo="5" turn="0" cursor="" onclick="-1" prefix="" subtitle="0xFFFFFF" mouse="1" float="0" tween="7" rotate="0" scroller="0" scale="" color="" rate="" blur="" />
          <vars />
          <title>
            <en><![CDATA[crates and fishing nets]]></en>
            <de><![CDATA[Kisten und Fischernetze]]></de>
          </title>
          <actions>
            <action id="act0">
              <title>
                <en><![CDATA[Look at]]></en>
                <de><![CDATA[Untersuche]]></de>
              </title>
              <dialog>
                <dia puppet="_avatar" frame="" sound="voice/docks3_voice.swf:docks30035">
                  <en><![CDATA[Hurray, more fishing gear!]]></en>
                  <de><![CDATA[Hurra, mehr Angelsachen!]]></de>
                </dia>
              </dialog>
              <script>
                <dialogue play="*" />
              </script>
            </action>
            <action id="act1">
              <title>
                <en><![CDATA[Talk to]]></en>
                <de><![CDATA[Sprich mit]]></de>
              </title>
              <dialog />
              <script>
                <dialogue play="*" />
              </script>
            </action>
            <action id="act2">
              <title>
                <en><![CDATA[Use]]></en>
                <de><![CDATA[Benutze]]></de>
              </title>
              <dialog>
                <dia puppet="_avatar" frame="" sound="voice/docks3_voice.swf:docks30036">
                  <en><![CDATA[I wouldn’t know where to begin.]]></en>
                  <de><![CDATA[Ich wüsste nicht, wo ich anfangen sollte.]]></de>
                </dia>
              </dialog>
              <script>
                <dialogue play="*" />
              </script>
            </action>
          </actions>
          <items />
        </state>
      </states>
    </layer>
    <layer id="rowboat" type="puppet" asset="lib/docks.swf:DocksBoatRepair" depth="15" visible="1" state="main">
      <states>
        <state id="main" x="210" y="954" img="1" imgX="-210" imgY="-157" imgW="1" imgH="1" frame="2" blend="normal" alpha="1" bitmap="0" hit="1" hitX="-209" hitY="-156" hitW="135" hitH="177" shape="rect">
          <param mapX="512" mapY="877" turnTo="5" turn="0" cursor="" onclick="-1" prefix="" subtitle="0xFFFFFF" mouse="1" float="1" tween="7" rotate="0" scroller="0" scale="" color="" rate="" blur="" />
          <vars />
          <title>
            <en><![CDATA[wrecked boat]]></en>
            <de><![CDATA[abgewracktes Boot]]></de>
          </title>
          <actions>
            <action id="act0">
              <title>
                <en><![CDATA[Look at]]></en>
                <de><![CDATA[Untersuche]]></de>
              </title>
              <dialog>
                <dia puppet="_avatar" frame="" sound="voice/docks3_voice.swf:docks30037">
                  <en><![CDATA[While I don’t profess to be a mariner, I do know a sinking ship when I see it.]]></en>
                  <de><![CDATA[Ich behaupte zwar nicht, ein Seemann zu sein, aber ich erkenne ein sinkendes Schiff, wenn ich eines sehe.]]></de>
                </dia>
              </dialog>
              <script>
                <dialogue play="*" />
              </script>
            </action>
            <action id="act1">
              <title>
                <en><![CDATA[Talk to]]></en>
                <de><![CDATA[Sprich mit]]></de>
              </title>
              <dialog />
              <script>
                <dialogue play="*" />
              </script>
            </action>
            <action id="act2">
              <title>
                <en><![CDATA[Use]]></en>
                <de><![CDATA[Benutze]]></de>
              </title>
              <dialog>
                <dia puppet="_avatar" frame="hspeak" sound="voice/docks3_voice.swf:docks30038">
                  <en><![CDATA[Ha ... you’re joking. ... right?]]></en>
                  <de><![CDATA[Ha ... Das ist ein Scherz. ... oder?]]></de>
                </dia>
              </dialog>
              <script>
                <dialogue play="*" />
              </script>
            </action>
          </actions>
          <items />
        </state>
      </states>
    </layer>
    <layer id="crates" type="puppet" asset="lib/docks.swf:DocksCrate" depth="16" visible="1" state="main">
      <states>
        <state id="main" x="299" y="1005" img="1" imgX="-16" imgY="-164" imgW="1" imgH="1" frame="2" blend="normal" alpha="1" bitmap="1" hit="1" hitX="-3" hitY="-104" hitW="104" hitH="152" shape="rect">
          <param mapX="265" mapY="990" turnTo="5" turn="0" cursor="" onclick="-1" prefix="" subtitle="0xFFFFFF" mouse="1" float="1" tween="7" rotate="0" scroller="0" scale="" color="" rate="" blur="" />
          <vars />
          <title>
            <en><![CDATA[crates]]></en>
            <de><![CDATA[Kisten]]></de>
          </title>
          <actions>
            <action id="act0">
              <title>
                <en><![CDATA[Look at]]></en>
                <de><![CDATA[Untersuche]]></de>
              </title>
              <dialog>
                <dia puppet="_avatar" frame="" sound="voice/docks3_voice.swf:docks30039">
                  <en><![CDATA[These crates smell of rotting wood, salt water, and fish... possibly worse than I do.]]></en>
                  <de><![CDATA[Diese Kisten riechen nach faulem Holz, Salzwasser und Fisch ... wahrscheinlich schlimmer als ich.]]></de>
                </dia>
              </dialog>
              <script>
                <dialogue play="*" />
              </script>
            </action>
            <action id="act1">
              <title>
                <en><![CDATA[Lick]]></en>
                <de><![CDATA[Schlecke an]]></de>
              </title>
              <dialog>
                <dia puppet="_avatar" frame="" sound="voice/docks3_voice.swf:docks30040">
                  <en><![CDATA[Yuck.]]></en>
                  <de><![CDATA[Igitt.]]></de>
                </dia>
              </dialog>
              <script>
                <dialogue play="*" />
              </script>
            </action>
            <action id="act2">
              <title>
                <en><![CDATA[Pick up]]></en>
                <de><![CDATA[Nimm]]></de>
              </title>
              <dialog>
                <dia puppet="_avatar" frame="lspeak4" sound="voice/docks3_voice.swf:docks30041">
                  <en><![CDATA[I do NOT need more smelly fishing inventory.]]></en>
                  <de><![CDATA[Ich brauche nicht NOCH mehr stinkendes Angelzubehör.]]></de>
                </dia>
              </dialog>
              <script>
                <dialogue play="*" />
              </script>
            </action>
          </actions>
          <items />
        </state>
      </states>
    </layer>
    <layer id="table" type="plane" asset="lib/docks.swf:DocksTable" depth="17" visible="1" state="main">
      <states>
        <state id="main" x="110" y="1113" img="1" imgX="-110" imgY="-225" imgW="1" imgH="1" frame="2" blend="normal" alpha="1" bitmap="1" hit="0" hitX="0" hitY="0" hitW="100" hitH="100" shape="rect">
          <param mouse="0" float="1" parallax="" />
          <vars />
          <title>
            <en><![CDATA[]]></en>
            <de><![CDATA[]]></de>
          </title>
          <actions />
          <items />
        </state>
      </states>
    </layer>
    <layer id="mcmanus" type="puppet" asset="lib/mcmanus.swf:McManusAct3" depth="18" visible="1" state="flashed">
      <states>
        <state id="flashed" x="601" y="1204" img="1" imgX="66" imgY="-370" imgW="-1.1" imgH="1.1" frame="1" blend="normal" alpha="1" bitmap="0" hit="1" hitX="-69" hitY="-361" hitW="120" hitH="340" shape="rect">
          <param mapX="414" mapY="1190" turnTo="5" turn="0" cursor="" onclick="-1" prefix="" subtitle="0x99CCCC" mouse="1" float="1" tween="7" rotate="0" scroller="0" scale="" color="" rate="" blur="" />
          <vars />
          <title>
            <en><![CDATA[McManus]]></en>
            <de><![CDATA[McManus]]></de>
          </title>
          <actions>
            <action id="act0">
              <title>
                <en><![CDATA[Look at]]></en>
                <de><![CDATA[Untersuche]]></de>
              </title>
              <dialog>
                <dia puppet="_avatar" frame="" sound="voice/docks3_voice.swf:docks30042">
                  <en><![CDATA[McManus is still under hypnosis ...]]></en>
                  <de><![CDATA[McManus steht noch unter Hypnose ...]]></de>
                </dia>
                <dia puppet="_avatar" frame="" sound="voice/docks3_voice.swf:docks30043">
                  <en><![CDATA[It’s horrible how confused he is. He’s been waiting with Shroom at the docks ever since we arrived here.]]></en>
                  <de><![CDATA[Es ist schrecklich, wie verwirrt er ist. Er wartet mit Shroom an den Docks, seit wir hier angekommen sind.]]></de>
                </dia>
                <dia puppet="_avatar" frame="" sound="voice/docks3_voice.swf:docks30044">
                  <en><![CDATA[I have to find a way to help him!]]></en>
                  <de><![CDATA[Ich muss eine Möglichkeit finden, ihm zu helfen!]]></de>
                </dia>
              </dialog>
              <script>
                <dialogue play="*" />
              </script>
            </action>
            <action id="act1">
              <title>
                <en><![CDATA[Talk to]]></en>
                <de><![CDATA[Sprich mit]]></de>
              </title>
              <dialog>
                <dia puppet="_avatar" frame="" sound="voice/docks3_voice.swf:docks30045">
                  <en><![CDATA[McManus, are you alright?]]></en>
                  <de><![CDATA[McManus, geht es Ihnen gut?]]></de>
                </dia>
                <dia puppet="mcmanus" frame="actIII_flashed_speak" sound="voice/docks3_voice.swf:docks30046">
                  <en><![CDATA[What I am doing here? ... and who are you?]]></en>
                  <de><![CDATA[Was mache ich hier? ... Und wer sind Sie?]]></de>
                </dia>
                <dia puppet="_avatar" frame="" sound="voice/docks3_voice.swf:docks30047">
                  <en><![CDATA[He is still suffering from the mind-altering effects of Lowell Cain’s hypnosis device.]]></en>
                  <de><![CDATA[Er leidet noch unter der bewusstseinsverändernden Wirkung von Lowell Cains Hypnosegerät.]]></de>
                </dia>
              </dialog>
              <script>
                <dialogue play="*" />
              </script>
            </action>
            <action id="act2">
              <title>
                <en><![CDATA[Use]]></en>
                <de><![CDATA[Benutze]]></de>
              </title>
              <dialog />
              <script>
                <dialogue play="*" />
              </script>
            </action>
          </actions>
          <items>
            <action id="flash_good">
              <title>
                <en><![CDATA[]]></en>
              </title>
              <dialog>
                <dia puppet="_avatar" frame="" sound="voice/docks3_voice.swf:docks30048">
                  <en><![CDATA[Say “cheese” ...]]></en>
                  <de><![CDATA[Sagen Sie “Cheese” ...]]></de>
                </dia>
                <dia puppet="mcmanus" frame="" sound="voice/docks3_voice.swf:docks30049">
                  <en><![CDATA[Gosh, by the unholy white whale and the seagulls that are follow’n him, what was that?]]></en>
                  <de><![CDATA[Donnerwetter! Beim gottlosen weißen Wal und den Möwen, die ihm folgen, was war das?]]></de>
                </dia>
                <dia puppet="_avatar" frame="" sound="voice/docks3_voice.swf:docks30050">
                  <en><![CDATA[You’ve been under a heavy hypnosis. Are you feeling any better?]]></en>
                  <de><![CDATA[Sie standen unter schwerer Hypnose. Geht es ihnen jetzt besser?]]></de>
                </dia>
                <dia puppet="mcmanus" frame="" sound="voice/docks3_voice.swf:docks30051">
                  <en><![CDATA[Aye, thanks to you, mate!]]></en>
                  <de><![CDATA[Jawohl, dank Ihnen, mein Freund!]]></de>
                </dia>
                <dia puppet="mcmanus" frame="lspeak" sound="voice/docks3_voice.swf:docks30052">
                  <en><![CDATA[The last thing I remember is Dr. Coppelius being kidnapped by those uniformed yellow-belly officials ...]]></en>
                  <de><![CDATA[Das letzte, woran ich mich erinnere, ist, dass Dr. Coppelius von diesen uniformierten, feigen Beamten entführt wurde ...]]></de>
                </dia>
                <dia puppet="_avatar" frame="" sound="voice/docks3_voice.swf:docks30053">
                  <en><![CDATA[Don’t worry, Dr. Coppelius and Nora are safe. Unfortunately Vincent is still on the run ... but we’re going after him.]]></en>
                  <de><![CDATA[Keine Sorge, Dr. Coppelius und Nora sind in Sicherheit. Leider ist Vincent noch auf der Flucht ... Aber wir verfolgen ihn.]]></de>
                </dia>
                <dia puppet="mcmanus" frame="" sound="voice/docks3_voice.swf:docks30054">
                  <en><![CDATA[Shroom and me, we’ll stay here for now if you don’t mind ... I still feel a bit foggy ’round me head, and we still have to repair our ship.]]></en>
                  <de><![CDATA[Wir bleiben hier, wenn es Ihnen nichts ausmacht ... Ich fühle mich noch ein bisschen vernebelt im Kopf, und wir müssen unser Schiff noch reparieren.]]></de>
                </dia>
                <dia puppet="mcmanus" frame="" sound="voice/docks3_voice.swf:docks30055">
                  <en><![CDATA[Just do me a favor, and give Vincent a good whacking with this when you find him. I won’t be forgett’n what he did to me Sea Cucumber.]]></en>
                  <de><![CDATA[Tun Sie mir einen Gefallen und verpassen Sie Vincent eine ordentliche Tracht Prügel, wenn Sie ihn finden. Ich werde nicht vergessen, was er meinem Schiff, der alten Seegurke, angetan hat.]]></de>
                </dia>
                <dia puppet="_avatar" frame="" sound="voice/docks3_voice.swf:docks30056">
                  <en><![CDATA[Okay ... of course ... we will meet again, McManus!]]></en>
                  <de><![CDATA[Ok ... natürlich ... wir sehen uns, McManus!]]></de>
                </dia>
                <dia puppet="mcmanus" frame="" sound="voice/docks3_voice.swf:docks30057">
                  <en><![CDATA[Indeed, we will! Take care, mate!]]></en>
                  <de><![CDATA[Ganz bestimmt! Passen Sie auf sich auf, mein Freund!]]></de>
                </dia>
              </dialog>
              <script>
                <method call="controls" enabled="0" />
                <dialogue playList="0" />
                <layerSprite target="_avatar" animFrame="reach_flashout" waitForComplete="1" />
                <layerSprite target="_avatar" animFrame="flash" waitForComplete="1" />
                <layerSprite target="mcmanus" animFrame="ACTIII_flashed_unflash" waitForComplete="1" />
                <layer target="_current:mcmanus" state="unflashed" />
                <layerSprite target="_avatar" animFrame="reach_flashin" waitForComplete="1" />
                <dialogue playList="1,2,3,4,5,6,7" />
                <layerSprite target="mcmanus" animFrame="giveout" waitForComplete="1" />
                <layerSprite target="_avatar" animFrame="reach_out" waitForComplete="1" />
                <layerSprite target="mcmanus" animFrame="givein" waitForComplete="0" />
                <layerSprite target="_avatar" animFrame="reach_in" waitForComplete="1" />
                <inventory add="gaff" />
                <method call="controls" enabled="1" />
                <dialogue play="8,9" />
              </script>
            </action>
            <action id="flash_bad">
              <title>
                <en><![CDATA[]]></en>
              </title>
              <dialog>
                <dia puppet="_avatar" frame="" sound="voice/docks3_voice.swf:docks30058">
                  <en><![CDATA[He’s had enough brainwashing.]]></en>
                  <de><![CDATA[Er hat genug Gehirnwäsche abbekommen.]]></de>
                </dia>
              </dialog>
              <script>
                <dialogue play="*" />
              </script>
            </action>
          </items>
        </state>
        <state id="unflashed" x="597" y="1204" img="1" imgX="70" imgY="-370" imgW="-1.1" imgH="1.1" frame="7" blend="normal" alpha="1" bitmap="0" hit="1" hitX="-62" hitY="-359" hitW="120" hitH="340" shape="rect">
          <param mapX="414" mapY="1190" turnTo="5" turn="0" cursor="" onclick="-1" prefix="actIII_normal_" subtitle="0x99CCCC" mouse="1" float="1" tween="7" rotate="0" scroller="0" scale="" color="" rate="" blur="" />
          <vars />
          <title>
            <en><![CDATA[McManus]]></en>
            <de><![CDATA[McManus]]></de>
          </title>
          <actions>
            <action id="act0">
              <title>
                <en><![CDATA[Look at]]></en>
                <de><![CDATA[Untersuche]]></de>
              </title>
              <dialog>
                <dia puppet="_avatar" frame="" sound="voice/docks3_voice.swf:docks30059">
                  <en><![CDATA[Finally, McManus is his old self again ...]]></en>
                  <de><![CDATA[Endlich ist McManus wieder der Alte ...]]></de>
                </dia>
              </dialog>
              <script>
                <dialogue play="*" />
              </script>
            </action>
            <action id="act1">
              <title>
                <en><![CDATA[Talk to]]></en>
                <de><![CDATA[Sprich mit]]></de>
              </title>
              <dialog>
                <dia puppet="_avatar" frame="" sound="voice/docks3_voice.swf:docks30060">
                  <en><![CDATA[We will meet again, MacManus!]]></en>
                  <de><![CDATA[Wir sehen uns wieder, McManus!]]></de>
                </dia>
                <dia puppet="mcmanus" frame="hspeak" sound="voice/docks3_voice.swf:docks30061">
                  <en><![CDATA[Indeed, we will! Take care, mate!]]></en>
                  <de><![CDATA[Ganz bestimmt! Passen Sie auf sich auf, mein Freund!]]></de>
                </dia>
              </dialog>
              <script>
                <dialogue play="*" />
              </script>
            </action>
            <action id="act2">
              <title>
                <en><![CDATA[Use]]></en>
                <de><![CDATA[Benutze]]></de>
              </title>
              <dialog />
              <script>
                <dialogue play="*" />
              </script>
            </action>
          </actions>
          <items />
        </state>
      </states>
    </layer>
    <layer id="shroom" type="puppet" asset="lib/shroom.swf:Shroom" depth="19" visible="1" state="main">
      <states>
        <state id="main" x="545" y="1230" img="1" imgX="92" imgY="-214" imgW="-1.26" imgH="1.26" frame="16" blend="normal" alpha="1" bitmap="0" hit="1" hitX="-76" hitY="-189" hitW="109" hitH="134" shape="rect">
          <param mapX="414" mapY="1190" turnTo="5" turn="0" cursor="" onclick="-1" prefix="sad_" subtitle="0xFFFFFF" mouse="1" float="1" tween="7" rotate="0" scroller="0" scale="" color="" rate="" blur="" />
          <vars />
          <title>
            <en><![CDATA[Shroom]]></en>
            <de><![CDATA[Shroom]]></de>
          </title>
          <actions>
            <action id="act0">
              <title>
                <en><![CDATA[Look at]]></en>
                <de><![CDATA[Untersuche]]></de>
              </title>
              <dialog>
                <dia puppet="_avatar" frame="" sound="voice/docks3_voice.swf:docks30062">
                  <en><![CDATA[Well, at least Shroom is okay.]]></en>
                  <de><![CDATA[Naja, wenigstens geht es Shroom gut.]]></de>
                </dia>
              </dialog>
              <script>
                <dialogue play="*" />
              </script>
            </action>
            <action id="act1">
              <title>
                <en><![CDATA[Talk to]]></en>
                <de><![CDATA[Sprich mit]]></de>
              </title>
              <dialog>
                <dia puppet="_avatar" frame="" sound="voice/docks3_voice.swf:docks30063">
                  <en><![CDATA[Hey, I hope you’re taking good care of your friend.]]></en>
                  <de><![CDATA[He, ich hoffe, du passt gut auf deinen Freund auf.]]></de>
                </dia>
                <dia puppet="shroom" frame="bark" sound="voice/docks3_voice.swf:docks30064">
                  <en><![CDATA[Woof!]]></en>
                  <de><![CDATA[Wuff!]]></de>
                </dia>
                <dia puppet="_avatar" frame="hspeak" sound="voice/docks3_voice.swf:docks30065">
                  <en><![CDATA[Good boy!]]></en>
                  <de><![CDATA[Braver Junge!]]></de>
                </dia>
              </dialog>
              <script>
                <dialogue playList="0" />
                <sound effect="lib/sound_effects.swf:dogBark" waitForComplete="0" />
                <dialogue playList="1,2" />
              </script>
            </action>
            <action id="act2">
              <title>
                <en><![CDATA[Use]]></en>
                <de><![CDATA[Benutze]]></de>
              </title>
              <dialog />
              <script>
                <dialogue play="*" />
              </script>
            </action>
          </actions>
          <items />
        </state>
      </states>
    </layer>
    <layer id="poster_group" type="puppet" asset="" depth="20" visible="1" state="main">
      <states>
        <state id="main" x="179" y="888" img="1" imgX="0" imgY="0" imgW="1" imgH="1" frame="1" blend="normal" alpha="1" bitmap="0" hit="1" hitX="-38" hitY="-171" hitW="81" hitH="137" shape="rect">
          <param mapX="143" mapY="921" turnTo="5" turn="0" cursor="" onclick="-1" prefix="" subtitle="0xFFFFFF" mouse="1" float="0" tween="7" rotate="0" scroller="0" scale="" color="" rate="" blur="" />
          <vars />
          <title>
            <en><![CDATA[castle posters]]></en>
            <de><![CDATA[Schloss-Poster]]></de>
          </title>
          <actions>
            <action id="act0">
              <title>
                <en><![CDATA[Look at]]></en>
                <de><![CDATA[Untersuche]]></de>
              </title>
              <dialog>
                <dia puppet="_avatar" frame="" sound="voice/docks3_voice.swf:docks30066">
                  <en><![CDATA[Wow, surviving Northwest castle posters!]]></en>
                  <de><![CDATA[Wow, noch ein paar Poster von Schloss Nordwest!]]></de>
                </dia>
                <dia puppet="_avatar" frame="" sound="voice/docks3_voice.swf:docks30067">
                  <en><![CDATA[I give them until the morning before the locals tear them down.]]></en>
                  <de><![CDATA[Ich gebe ihnen bis morgen früh, ehe die Dorfbewohner sie abreißen.]]></de>
                </dia>
              </dialog>
              <script>
                <dialogue play="*" />
              </script>
            </action>
            <action id="act1">
              <title>
                <en><![CDATA[Talk to]]></en>
                <de><![CDATA[Sprich mit]]></de>
              </title>
              <dialog />
              <script>
                <dialogue play="*" />
              </script>
            </action>
            <action id="act2">
              <title>
                <en><![CDATA[Tear down]]></en>
                <de><![CDATA[Entferne]]></de>
              </title>
              <dialog>
                <dia puppet="_avatar" frame="" sound="voice/docks3_voice.swf:docks30068">
                  <en><![CDATA[Naw, I’ll save the satisfaction for the locals.]]></en>
                  <de><![CDATA[Nein, diese Befriedigung überlasse ich den Dorfbewohnern.]]></de>
                </dia>
              </dialog>
              <script>
                <dialogue play="*" />
              </script>
            </action>
          </actions>
          <items />
        </state>
      </states>
    </layer>
    <layer id="poster" type="puppet" asset="" depth="21" visible="1" state="main">
      <states>
        <state id="main" x="417" y="829" img="1" imgX="0" imgY="0" imgW="1" imgH="1" frame="1" blend="normal" alpha="1" bitmap="0" hit="1" hitX="10" hitY="-111" hitW="41" hitH="58" shape="rect">
          <param mapX="405" mapY="840" turnTo="5" turn="0" cursor="" onclick="-1" prefix="" subtitle="0xFFFFFF" mouse="1" float="0" tween="7" rotate="0" scroller="0" scale="" color="" rate="" blur="" />
          <vars />
          <title>
            <en><![CDATA[poster]]></en>
            <de><![CDATA[Poster]]></de>
          </title>
          <actions>
            <action id="act0">
              <title>
                <en><![CDATA[Look at]]></en>
                <de><![CDATA[Untersuche]]></de>
              </title>
              <dialog>
                <dia puppet="_avatar" frame="" sound="voice/docks3_voice.swf:docks30069">
                  <en><![CDATA[This poster’s message is now outdated. The power of Northwest Castle is no more!]]></en>
                  <de><![CDATA[Die Botschaft dieses Posters ist jetzt veraltet. Die Macht von Schloss Nordwest ist gebrochen!]]></de>
                </dia>
              </dialog>
              <script>
                <dialogue play="*" />
              </script>
            </action>
            <action id="act1">
              <title>
                <en><![CDATA[Talk to]]></en>
                <de><![CDATA[Sprich mit]]></de>
              </title>
              <dialog />
              <script>
                <dialogue play="*" />
              </script>
            </action>
            <action id="act2">
              <title>
                <en><![CDATA[Take]]></en>
                <de><![CDATA[Nimm]]></de>
              </title>
              <dialog>
                <dia puppet="_avatar" frame="" sound="voice/docks3_voice.swf:docks30070">
                  <en><![CDATA[Naw, I don’t need any memorabilia of the regime.]]></en>
                  <de><![CDATA[Nein, ich brauche keine Andenken an das Regime.]]></de>
                </dia>
              </dialog>
              <script>
                <dialogue play="*" />
              </script>
            </action>
          </actions>
          <items />
        </state>
      </states>
    </layer>
    <layer id="boathouse_door" type="puppet" asset="lib/docks.swf:DocksBoathouseDoor" depth="22" visible="1" state="open">
      <states>
        <state id="open" x="516" y="825" img="1" imgX="-4" imgY="50" imgW="1" imgH="1" frame="3" blend="normal" alpha="1" bitmap="0" hit="1" hitX="-22" hitY="-100" hitW="60" hitH="106" shape="rect">
          <param mapX="560" mapY="805" turnTo="5" turn="0" cursor="exit3" onclick="0" prefix="" subtitle="0xFFFFFF" mouse="1" float="0" tween="7" rotate="0" scroller="0" scale="" color="" rate="" blur="" />
          <vars />
          <title>
            <en><![CDATA[]]></en>
            <de><![CDATA[]]></de>
          </title>
          <actions>
            <action id="act0">
              <title>
                <en><![CDATA[Look at]]></en>
                <de><![CDATA[Untersuche]]></de>
              </title>
              <dialog />
              <script>
                <game room="boathouse3:join_docks" />
              </script>
            </action>
            <action id="act1">
              <title>
                <en><![CDATA[Talk to]]></en>
                <de><![CDATA[Sprich mit]]></de>
              </title>
              <dialog />
              <script>
                <dialogue play="*" />
              </script>
            </action>
            <action id="act2">
              <title>
                <en><![CDATA[Use]]></en>
                <de><![CDATA[Benutze]]></de>
              </title>
              <dialog />
              <script>
                <dialogue play="*" />
              </script>
            </action>
          </actions>
          <items />
        </state>
      </states>
    </layer>
    <layer id="rain_barrel" type="puppet" asset="" depth="23" visible="1" state="main">
      <states>
        <state id="main" x="451" y="823" img="1" imgX="0" imgY="0" imgW="1" imgH="1" frame="1" blend="normal" alpha="1" bitmap="0" hit="1" hitX="-12" hitY="-52" hitW="51" hitH="61" shape="rect">
          <param mapX="454" mapY="854" turnTo="5" turn="0" cursor="" onclick="-1" prefix="" subtitle="0xFFFFFF" mouse="1" float="0" tween="7" rotate="0" scroller="0" scale="" color="" rate="" blur="" />
          <vars />
          <title>
            <en><![CDATA[rain barrel]]></en>
            <de><![CDATA[Regenfass]]></de>
          </title>
          <actions>
            <action id="act0">
              <title>
                <en><![CDATA[Look at]]></en>
                <de><![CDATA[Untersuche]]></de>
              </title>
              <dialog>
                <dia puppet="_avatar" frame="" sound="voice/docks3_voice.swf:docks30071">
                  <en><![CDATA[Haha! This barrel may become Lowel Cain’s new wardrobe.]]></en>
                  <de><![CDATA[Haha! Dieses Fass könnte Lowell Cains neues Outfit werden.]]></de>
                </dia>
              </dialog>
              <script>
                <dialogue play="*" />
              </script>
            </action>
            <action id="act1">
              <title>
                <en><![CDATA[Drink from]]></en>
                <de><![CDATA[Trinke aus]]></de>
              </title>
              <dialog>
                <dia puppet="_avatar" frame="" sound="voice/docks3_voice.swf:docks30072">
                  <en><![CDATA[No, I have to question the cleanliness of stagnant water reserves.]]></en>
                  <de><![CDATA[Nein, ich muss an der Reinheit von gammelnden Wasservorräten zweifeln.]]></de>
                </dia>
              </dialog>
              <script>
                <dialogue play="*" />
              </script>
            </action>
            <action id="act2">
              <title>
                <en><![CDATA[Push]]></en>
                <de><![CDATA[Schiebe]]></de>
              </title>
              <dialog>
                <dia puppet="_avatar" frame="" sound="voice/docks3_voice.swf:docks30073">
                  <en><![CDATA[I’ll let it be.]]></en>
                  <de><![CDATA[Ich lasse es sein.]]></de>
                </dia>
              </dialog>
              <script>
                <dialogue play="*" />
              </script>
            </action>
          </actions>
          <items />
        </state>
      </states>
    </layer>
    <layer id="_avatar" type="avatar" asset="lib/nigel.swf:Nigel" depth="24" visible="1" state="main">
      <states>
        <state id="main" x="132" y="1188" img="1" imgX="3" imgY="12" imgW="1" imgH="1" frame="1" blend="normal" alpha="1" bitmap="0" hit="0" hitX="0" hitY="0" hitW="100" hitH="100" shape="rect">
          <param scroller="1" float="1" mouse="0" tween="7" scale="baseScale" color="" rate="" blur="" />
          <vars />
          <title>
            <en><![CDATA[nigel]]></en>
          </title>
          <actions />
          <items />
        </state>
      </states>
    </layer>
    <layer id="boathouse" type="puppet" asset="lib/docks.swf:DocksBoathouse" depth="25" visible="1" state="main">
      <states>
        <state id="main" x="530" y="828" img="1" imgX="-24" imgY="-133" imgW="1" imgH="1" frame="2" blend="normal" alpha="1" bitmap="1" hit="1" hitX="12" hitY="-153" hitW="109" hitH="169" shape="rect">
          <param mapX="489" mapY="838" turnTo="5" turn="0" cursor="" onclick="-1" prefix="" subtitle="0xFFFFFF" mouse="1" float="0" tween="7" rotate="0" scroller="0" scale="" color="" rate="" blur="" />
          <vars />
          <title>
            <en><![CDATA[boathouse]]></en>
            <de><![CDATA[Bootshaus]]></de>
          </title>
          <actions>
            <action id="act0">
              <title>
                <en><![CDATA[Look at]]></en>
                <de><![CDATA[Untersuche]]></de>
              </title>
              <dialog>
                <dia puppet="_avatar" frame="" sound="voice/docks3_voice.swf:docks30074">
                  <en><![CDATA[Boathouse number 8... or infinity if you turn your head and squint at it.]]></en>
                  <de><![CDATA[Bootshaus Nummer 8 ... oder das Zeichen der Unendlichkeit, wenn man den Kopf so hält und die Augen zusammenkneift]]></de>
                </dia>
              </dialog>
              <script>
                <dialogue play="*" />
              </script>
            </action>
            <action id="act1">
              <title>
                <en><![CDATA[Talk to]]></en>
                <de><![CDATA[Sprich mit]]></de>
              </title>
              <dialog />
              <script>
                <dialogue play="*" />
              </script>
            </action>
            <action id="act2">
              <title>
                <en><![CDATA[Use]]></en>
                <de><![CDATA[Benutze]]></de>
              </title>
              <dialog />
              <script>
                <dialogue play="*" />
              </script>
            </action>
          </actions>
          <items />
        </state>
      </states>
    </layer>
    <layer id="starfish" type="plane" asset="lib/docks.swf:DocksFg" depth="26" visible="1" state="main">
      <states>
        <state id="main" x="0" y="1330" img="1" imgX="0" imgY="-95" imgW="1" imgH="1" frame="2" blend="normal" alpha="1" bitmap="1" hit="0" hitX="0" hitY="0" hitW="100" hitH="100" shape="rect">
          <param mouse="0" float="0" parallax="" />
          <vars />
          <title>
            <en><![CDATA[]]></en>
            <de><![CDATA[]]></de>
          </title>
          <actions />
          <items />
        </state>
      </states>
    </layer>
    <layer id="exit_ground1" type="puppet" asset="" depth="27" visible="0" state="main">
      <states>
        <state id="main" x="212" y="635" img="1" imgX="0" imgY="0" imgW="1" imgH="1" frame="1" blend="normal" alpha="1" bitmap="0" hit="1" hitX="-212" hitY="0" hitW="1024" hitH="150" shape="rect">
          <param mapX="180" mapY="343" turnTo="5" turn="0" cursor="exit5" onclick="0" prefix="" subtitle="0xFFFFFF" mouse="1" float="0" tween="7" rotate="0" scroller="0" scale="" color="" rate="" blur="" />
          <vars />
          <title>
            <en><![CDATA[]]></en>
            <de><![CDATA[]]></de>
          </title>
          <actions>
            <action id="act0">
              <title>
                <en><![CDATA[Look at]]></en>
                <de><![CDATA[Untersuche]]></de>
              </title>
              <dialog />
              <script>
                <method call="controls" enabled="0" />
                <layer target="_current:exit_ground1" visible="0" />
                <layer target="_current:exit_ground2" visible="0" />
                <layerState target="_current:lighthouse_tower:main" mouseEnabled="1" />
                <layerState target="_current:lighthouse_oil:main" mouseEnabled="1" />
                <layerState target="_current:windmill:main" mouseEnabled="1" />
                <puppetTween target="_avatar" type="move" to="position:lighthouse_bottom" waitForComplete="1" />
                <room target="_current" grid="main" />
                <method call="controls" enabled="1" />
              </script>
            </action>
            <action id="act1">
              <title>
                <en><![CDATA[Talk to]]></en>
                <de><![CDATA[Sprich mit]]></de>
              </title>
              <dialog />
              <script>
                <dialogue play="*" />
              </script>
            </action>
            <action id="act2">
              <title>
                <en><![CDATA[Use]]></en>
                <de><![CDATA[Benutze]]></de>
              </title>
              <dialog />
              <script>
                <dialogue play="*" />
              </script>
            </action>
          </actions>
          <items />
        </state>
      </states>
    </layer>
  </layers>
  <trees />
</room>