<localize>
  <NOUNS><![CDATA[
		Nouns state the title of an object that the player can mouse-over and interact with.
		These are generally singular nouns.
		Nouns may be blank.
]]></NOUNS>
  <n>
    <n0>
      <en><![CDATA[]]></en>
      <de><![CDATA[]]></de>
      <fr><![CDATA[]]></fr>
      <it><![CDATA[]]></it>
      <ru><![CDATA[]]></ru>
      <es><![CDATA[]]></es>
    </n0>
    <n1>
      <en><![CDATA[]]></en>
      <de><![CDATA[]]></de>
      <fr><![CDATA[]]></fr>
      <it><![CDATA[]]></it>
      <ru><![CDATA[]]></ru>
      <es><![CDATA[]]></es>
    </n1>
    <n2>
      <en><![CDATA[]]></en>
      <de><![CDATA[]]></de>
      <fr><![CDATA[]]></fr>
      <it><![CDATA[]]></it>
      <ru><![CDATA[]]></ru>
      <es><![CDATA[]]></es>
    </n2>
    <n3>
      <en><![CDATA[]]></en>
      <de><![CDATA[]]></de>
      <fr><![CDATA[]]></fr>
      <it><![CDATA[]]></it>
      <ru><![CDATA[]]></ru>
      <es><![CDATA[]]></es>
    </n3>
    <n4>
      <en><![CDATA[boat]]></en>
      <de><![CDATA[]]></de>
      <fr><![CDATA[]]></fr>
      <it><![CDATA[]]></it>
      <ru><![CDATA[лодка]]></ru>
      <es><![CDATA[]]></es>
    </n4>
    <n5>
      <en><![CDATA[lighthouse door]]></en>
      <de><![CDATA[]]></de>
      <fr><![CDATA[]]></fr>
      <it><![CDATA[]]></it>
      <ru><![CDATA[дверь маяка]]></ru>
      <es><![CDATA[]]></es>
    </n5>
    <n6>
      <en><![CDATA[Ravenhollow Harbor]]></en>
      <de><![CDATA[]]></de>
      <fr><![CDATA[]]></fr>
      <it><![CDATA[]]></it>
      <ru><![CDATA[Бухта Рэйвенхоллоу]]></ru>
      <es><![CDATA[]]></es>
    </n6>
    <n7>
      <en><![CDATA[boat patch]]></en>
      <de><![CDATA[]]></de>
      <fr><![CDATA[]]></fr>
      <it><![CDATA[]]></it>
      <ru><![CDATA[латка]]></ru>
      <es><![CDATA[]]></es>
    </n7>
    <n8>
      <en><![CDATA[bucket o’ tar]]></en>
      <de><![CDATA[]]></de>
      <fr><![CDATA[]]></fr>
      <it><![CDATA[]]></it>
      <ru><![CDATA[ведро смолы]]></ru>
      <es><![CDATA[]]></es>
    </n8>
    <n9>
      <en><![CDATA[boathouse]]></en>
      <de><![CDATA[]]></de>
      <fr><![CDATA[]]></fr>
      <it><![CDATA[]]></it>
      <ru><![CDATA[лодочный сарай]]></ru>
      <es><![CDATA[]]></es>
    </n9>
    <n10>
      <en><![CDATA[Mr. McManus]]></en>
      <de><![CDATA[]]></de>
      <fr><![CDATA[]]></fr>
      <it><![CDATA[]]></it>
      <ru><![CDATA[мистер Макманус]]></ru>
      <es><![CDATA[]]></es>
    </n10>
    <n11>
      <en><![CDATA[Grandpa]]></en>
      <de><![CDATA[]]></de>
      <fr><![CDATA[]]></fr>
      <it><![CDATA[]]></it>
      <ru><![CDATA[Дедушка]]></ru>
      <es><![CDATA[]]></es>
    </n11>
    <n12>
      <en><![CDATA[Shroom]]></en>
      <de><![CDATA[]]></de>
      <fr><![CDATA[]]></fr>
      <it><![CDATA[]]></it>
      <ru><![CDATA[Грибок]]></ru>
      <es><![CDATA[]]></es>
    </n12>
    <n13>
      <en><![CDATA[barrel]]></en>
      <de><![CDATA[]]></de>
      <fr><![CDATA[]]></fr>
      <it><![CDATA[]]></it>
      <ru><![CDATA[бочка]]></ru>
      <es><![CDATA[]]></es>
    </n13>
    <n14>
      <en><![CDATA[barrel]]></en>
      <de><![CDATA[]]></de>
      <fr><![CDATA[]]></fr>
      <it><![CDATA[]]></it>
      <ru><![CDATA[бочка]]></ru>
      <es><![CDATA[]]></es>
    </n14>
    <n15>
      <en><![CDATA[huge castle guard]]></en>
      <de><![CDATA[]]></de>
      <fr><![CDATA[]]></fr>
      <it><![CDATA[]]></it>
      <ru><![CDATA[бугай-охранник из замка]]></ru>
      <es><![CDATA[]]></es>
    </n15>
    <n16>
      <en><![CDATA[Nigel Trelawney]]></en>
      <de><![CDATA[]]></de>
      <fr><![CDATA[]]></fr>
      <it><![CDATA[]]></it>
      <ru><![CDATA[Найджел Трелони]]></ru>
      <es><![CDATA[]]></es>
    </n16>
    <n17>
      <en><![CDATA[Lowell Cain]]></en>
      <de><![CDATA[]]></de>
      <fr><![CDATA[]]></fr>
      <it><![CDATA[]]></it>
      <ru><![CDATA[Лоуэлл Кейн]]></ru>
      <es><![CDATA[]]></es>
    </n17>
  </n>
  <VERBS><![CDATA[
		A verb summary describes an interaction that the player can perform on an object.
		Formatting of the verb/noun wording is controlled globally through the verb dialect field.
		Global verb dialect allows you to specify a "#verb# #noun#" formatting string that will govern how all verbs and nouns are joined together.
]]></VERBS>
  <v>
    <v0 noun="">
      <en><![CDATA[Look at]]></en>
      <de><![CDATA[]]></de>
      <fr><![CDATA[]]></fr>
      <it><![CDATA[]]></it>
      <ru><![CDATA[Осмотреть:]]></ru>
      <es><![CDATA[]]></es>
    </v0>
    <v1 noun="">
      <en><![CDATA[Talk to]]></en>
      <de><![CDATA[]]></de>
      <fr><![CDATA[]]></fr>
      <it><![CDATA[]]></it>
      <ru><![CDATA[Поговорить:]]></ru>
      <es><![CDATA[]]></es>
    </v1>
    <v2 noun="">
      <en><![CDATA[Use]]></en>
      <de><![CDATA[]]></de>
      <fr><![CDATA[]]></fr>
      <it><![CDATA[]]></it>
      <ru><![CDATA[Использовать:]]></ru>
      <es><![CDATA[]]></es>
    </v2>
    <v3 noun="boat">
      <en><![CDATA[Look at]]></en>
      <de><![CDATA[]]></de>
      <fr><![CDATA[]]></fr>
      <it><![CDATA[]]></it>
      <ru><![CDATA[Осмотреть:]]></ru>
      <es><![CDATA[]]></es>
    </v3>
    <v4 noun="boat">
      <en><![CDATA[Talk to]]></en>
      <de><![CDATA[]]></de>
      <fr><![CDATA[]]></fr>
      <it><![CDATA[]]></it>
      <ru><![CDATA[Поговорить:]]></ru>
      <es><![CDATA[]]></es>
    </v4>
    <v5 noun="boat">
      <en><![CDATA[Use]]></en>
      <de><![CDATA[]]></de>
      <fr><![CDATA[]]></fr>
      <it><![CDATA[]]></it>
      <ru><![CDATA[Использовать:]]></ru>
      <es><![CDATA[]]></es>
    </v5>
    <v6 noun="lighthouse door">
      <en><![CDATA[Look at]]></en>
      <de><![CDATA[]]></de>
      <fr><![CDATA[]]></fr>
      <it><![CDATA[]]></it>
      <ru><![CDATA[Осмотреть:]]></ru>
      <es><![CDATA[]]></es>
    </v6>
    <v7 noun="lighthouse door">
      <en><![CDATA[Talk to]]></en>
      <de><![CDATA[]]></de>
      <fr><![CDATA[]]></fr>
      <it><![CDATA[]]></it>
      <ru><![CDATA[Поговорить:]]></ru>
      <es><![CDATA[]]></es>
    </v7>
    <v8 noun="lighthouse door">
      <en><![CDATA[Open]]></en>
      <de><![CDATA[]]></de>
      <fr><![CDATA[]]></fr>
      <it><![CDATA[]]></it>
      <ru><![CDATA[Открыть:]]></ru>
      <es><![CDATA[]]></es>
    </v8>
    <v9 noun="Ravenhollow Harbor">
      <en><![CDATA[Look at]]></en>
      <de><![CDATA[]]></de>
      <fr><![CDATA[]]></fr>
      <it><![CDATA[]]></it>
      <ru><![CDATA[Осмотреть:]]></ru>
      <es><![CDATA[]]></es>
    </v9>
    <v10 noun="Ravenhollow Harbor">
      <en><![CDATA[Talk to]]></en>
      <de><![CDATA[]]></de>
      <fr><![CDATA[]]></fr>
      <it><![CDATA[]]></it>
      <ru><![CDATA[Поговорить:]]></ru>
      <es><![CDATA[]]></es>
    </v10>
    <v11 noun="Ravenhollow Harbor">
      <en><![CDATA[Enter]]></en>
      <de><![CDATA[]]></de>
      <fr><![CDATA[]]></fr>
      <it><![CDATA[]]></it>
      <ru><![CDATA[Войти:]]></ru>
      <es><![CDATA[]]></es>
    </v11>
    <v12 noun="boat patch">
      <en><![CDATA[Look at]]></en>
      <de><![CDATA[]]></de>
      <fr><![CDATA[]]></fr>
      <it><![CDATA[]]></it>
      <ru><![CDATA[Осмотреть:]]></ru>
      <es><![CDATA[]]></es>
    </v12>
    <v13 noun="boat patch">
      <en><![CDATA[Talk to]]></en>
      <de><![CDATA[]]></de>
      <fr><![CDATA[]]></fr>
      <it><![CDATA[]]></it>
      <ru><![CDATA[Поговорить:]]></ru>
      <es><![CDATA[]]></es>
    </v13>
    <v14 noun="boat patch">
      <en><![CDATA[pick up]]></en>
      <de><![CDATA[]]></de>
      <fr><![CDATA[]]></fr>
      <it><![CDATA[]]></it>
      <ru><![CDATA[Поднять:]]></ru>
      <es><![CDATA[]]></es>
    </v14>
    <v15 noun="bucket o’ tar">
      <en><![CDATA[Look at]]></en>
      <de><![CDATA[]]></de>
      <fr><![CDATA[]]></fr>
      <it><![CDATA[]]></it>
      <ru><![CDATA[Осмотреть:]]></ru>
      <es><![CDATA[]]></es>
    </v15>
    <v16 noun="bucket o’ tar">
      <en><![CDATA[Talk to]]></en>
      <de><![CDATA[]]></de>
      <fr><![CDATA[]]></fr>
      <it><![CDATA[]]></it>
      <ru><![CDATA[Поговорить:]]></ru>
      <es><![CDATA[]]></es>
    </v16>
    <v17 noun="bucket o’ tar">
      <en><![CDATA[pick up]]></en>
      <de><![CDATA[]]></de>
      <fr><![CDATA[]]></fr>
      <it><![CDATA[]]></it>
      <ru><![CDATA[Поднять:]]></ru>
      <es><![CDATA[]]></es>
    </v17>
    <v18 noun="boathouse">
      <en><![CDATA[Look at]]></en>
      <de><![CDATA[]]></de>
      <fr><![CDATA[]]></fr>
      <it><![CDATA[]]></it>
      <ru><![CDATA[Осмотреть:]]></ru>
      <es><![CDATA[]]></es>
    </v18>
    <v19 noun="boathouse">
      <en><![CDATA[Talk to]]></en>
      <de><![CDATA[]]></de>
      <fr><![CDATA[]]></fr>
      <it><![CDATA[]]></it>
      <ru><![CDATA[Поговорить:]]></ru>
      <es><![CDATA[]]></es>
    </v19>
    <v20 noun="boathouse">
      <en><![CDATA[break through wall of]]></en>
      <de><![CDATA[]]></de>
      <fr><![CDATA[]]></fr>
      <it><![CDATA[]]></it>
      <ru><![CDATA[пробить стену]]></ru>
      <es><![CDATA[]]></es>
    </v20>
    <v21 noun="Mr. McManus">
      <en><![CDATA[Look at]]></en>
      <de><![CDATA[]]></de>
      <fr><![CDATA[]]></fr>
      <it><![CDATA[]]></it>
      <ru><![CDATA[Осмотреть:]]></ru>
      <es><![CDATA[]]></es>
    </v21>
    <v22 noun="Mr. McManus">
      <en><![CDATA[Call to]]></en>
      <de><![CDATA[]]></de>
      <fr><![CDATA[]]></fr>
      <it><![CDATA[]]></it>
      <ru><![CDATA[Позвать:]]></ru>
      <es><![CDATA[]]></es>
    </v22>
    <v23 noun="Mr. McManus">
      <en><![CDATA[Use]]></en>
      <de><![CDATA[]]></de>
      <fr><![CDATA[]]></fr>
      <it><![CDATA[]]></it>
      <ru><![CDATA[Использовать:]]></ru>
      <es><![CDATA[]]></es>
    </v23>
    <v25 noun="Grandpa">
      <en><![CDATA[Look at]]></en>
      <de><![CDATA[]]></de>
      <fr><![CDATA[]]></fr>
      <it><![CDATA[]]></it>
      <ru><![CDATA[Осмотреть:]]></ru>
      <es><![CDATA[]]></es>
    </v25>
    <v26 noun="Grandpa">
      <en><![CDATA[Talk to]]></en>
      <de><![CDATA[]]></de>
      <fr><![CDATA[]]></fr>
      <it><![CDATA[]]></it>
      <ru><![CDATA[Поговорить:]]></ru>
      <es><![CDATA[]]></es>
    </v26>
    <v27 noun="Grandpa">
      <en><![CDATA[Use]]></en>
      <de><![CDATA[]]></de>
      <fr><![CDATA[]]></fr>
      <it><![CDATA[]]></it>
      <ru><![CDATA[Использовать:]]></ru>
      <es><![CDATA[]]></es>
    </v27>
    <v29 noun="Shroom">
      <en><![CDATA[Look at]]></en>
      <de><![CDATA[]]></de>
      <fr><![CDATA[]]></fr>
      <it><![CDATA[]]></it>
      <ru><![CDATA[Осмотреть:]]></ru>
      <es><![CDATA[]]></es>
    </v29>
    <v30 noun="Shroom">
      <en><![CDATA[Call to]]></en>
      <de><![CDATA[]]></de>
      <fr><![CDATA[]]></fr>
      <it><![CDATA[]]></it>
      <ru><![CDATA[Позвать:]]></ru>
      <es><![CDATA[]]></es>
    </v30>
    <v31 noun="Shroom">
      <en><![CDATA[Use]]></en>
      <de><![CDATA[]]></de>
      <fr><![CDATA[]]></fr>
      <it><![CDATA[]]></it>
      <ru><![CDATA[Использовать:]]></ru>
      <es><![CDATA[]]></es>
    </v31>
    <v33 noun="barrel">
      <en><![CDATA[Look at]]></en>
      <de><![CDATA[]]></de>
      <fr><![CDATA[]]></fr>
      <it><![CDATA[]]></it>
      <ru><![CDATA[Осмотреть:]]></ru>
      <es><![CDATA[]]></es>
    </v33>
    <v34 noun="barrel">
      <en><![CDATA[Talk to]]></en>
      <de><![CDATA[]]></de>
      <fr><![CDATA[]]></fr>
      <it><![CDATA[]]></it>
      <ru><![CDATA[Поговорить:]]></ru>
      <es><![CDATA[]]></es>
    </v34>
    <v35 noun="barrel">
      <en><![CDATA[Take object from]]></en>
      <de><![CDATA[]]></de>
      <fr><![CDATA[]]></fr>
      <it><![CDATA[]]></it>
      <ru><![CDATA[Взять предмет у персонажа]]></ru>
      <es><![CDATA[]]></es>
    </v35>
    <v36 noun="barrel">
      <en><![CDATA[Look at]]></en>
      <de><![CDATA[]]></de>
      <fr><![CDATA[]]></fr>
      <it><![CDATA[]]></it>
      <ru><![CDATA[Осмотреть:]]></ru>
      <es><![CDATA[]]></es>
    </v36>
    <v37 noun="barrel">
      <en><![CDATA[Talk to]]></en>
      <de><![CDATA[]]></de>
      <fr><![CDATA[]]></fr>
      <it><![CDATA[]]></it>
      <ru><![CDATA[Поговорить:]]></ru>
      <es><![CDATA[]]></es>
    </v37>
    <v38 noun="barrel">
      <en><![CDATA[Take object from]]></en>
      <de><![CDATA[]]></de>
      <fr><![CDATA[]]></fr>
      <it><![CDATA[]]></it>
      <ru><![CDATA[Взять предмет у персонажа]]></ru>
      <es><![CDATA[]]></es>
    </v38>
    <v39 noun="huge castle guard">
      <en><![CDATA[Look at]]></en>
      <de><![CDATA[]]></de>
      <fr><![CDATA[]]></fr>
      <it><![CDATA[]]></it>
      <ru><![CDATA[Осмотреть:]]></ru>
      <es><![CDATA[]]></es>
    </v39>
    <v40 noun="huge castle guard">
      <en><![CDATA[Talk to]]></en>
      <de><![CDATA[]]></de>
      <fr><![CDATA[]]></fr>
      <it><![CDATA[]]></it>
      <ru><![CDATA[Поговорить:]]></ru>
      <es><![CDATA[]]></es>
    </v40>
    <v41 noun="huge castle guard">
      <en><![CDATA[Use]]></en>
      <de><![CDATA[]]></de>
      <fr><![CDATA[]]></fr>
      <it><![CDATA[]]></it>
      <ru><![CDATA[Использовать:]]></ru>
      <es><![CDATA[]]></es>
    </v41>
    <v43 noun="Nigel Trelawney">
      <en><![CDATA[Look at]]></en>
      <de><![CDATA[]]></de>
      <fr><![CDATA[]]></fr>
      <it><![CDATA[]]></it>
      <ru><![CDATA[Осмотреть:]]></ru>
      <es><![CDATA[]]></es>
    </v43>
    <v44 noun="Nigel Trelawney">
      <en><![CDATA[Talk to]]></en>
      <de><![CDATA[]]></de>
      <fr><![CDATA[]]></fr>
      <it><![CDATA[]]></it>
      <ru><![CDATA[Поговорить:]]></ru>
      <es><![CDATA[]]></es>
    </v44>
    <v45 noun="Nigel Trelawney">
      <en><![CDATA[Use]]></en>
      <de><![CDATA[]]></de>
      <fr><![CDATA[]]></fr>
      <it><![CDATA[]]></it>
      <ru><![CDATA[Использовать:]]></ru>
      <es><![CDATA[]]></es>
    </v45>
    <v47 noun="Lowell Cain">
      <en><![CDATA[Look at]]></en>
      <de><![CDATA[]]></de>
      <fr><![CDATA[]]></fr>
      <it><![CDATA[]]></it>
      <ru><![CDATA[Осмотреть:]]></ru>
      <es><![CDATA[]]></es>
    </v47>
    <v48 noun="Lowell Cain">
      <en><![CDATA[Talk to]]></en>
      <de><![CDATA[]]></de>
      <fr><![CDATA[]]></fr>
      <it><![CDATA[]]></it>
      <ru><![CDATA[Поговорить:]]></ru>
      <es><![CDATA[]]></es>
    </v48>
    <v49 noun="Lowell Cain">
      <en><![CDATA[Use]]></en>
      <de><![CDATA[]]></de>
      <fr><![CDATA[]]></fr>
      <it><![CDATA[]]></it>
      <ru><![CDATA[Использовать:]]></ru>
      <es><![CDATA[]]></es>
    </v49>
  </v>
  <CONTEXTS><![CDATA[
		A contextual summary describes an item's interaction with an object.
		This summary includes placeholder tokens (#noun# and #item#) for dynamic elements in the sentence.
		When translating, you may change the order and/or position of the placeholder tokens within the sentence.
		However, **DO NOT** translate the placeholder token text. They MUST be left as #noun# and #item#.
]]></CONTEXTS>
  <c>
    <c24 noun="Mr. McManus" item="slingshot_shells">
      <en><![CDATA[Shoot #item# at #noun#]]></en>
      <de><![CDATA[]]></de>
      <fr><![CDATA[]]></fr>
      <it><![CDATA[]]></it>
      <ru><![CDATA[#item#: выстрелить в цель (#noun#)]]></ru>
      <es><![CDATA[]]></es>
    </c24>
    <c28 noun="Grandpa" item="slingshot_shells">
      <en><![CDATA[Shoot #item# at #noun#]]></en>
      <de><![CDATA[]]></de>
      <fr><![CDATA[]]></fr>
      <it><![CDATA[]]></it>
      <ru><![CDATA[#item#: выстрелить в цель (#noun#)]]></ru>
      <es><![CDATA[]]></es>
    </c28>
    <c32 noun="Shroom" item="slingshot_shells">
      <en><![CDATA[Shoot #item# at #noun#]]></en>
      <de><![CDATA[]]></de>
      <fr><![CDATA[]]></fr>
      <it><![CDATA[]]></it>
      <ru><![CDATA[#item#: выстрелить в цель (#noun#)]]></ru>
      <es><![CDATA[]]></es>
    </c32>
    <c42 noun="huge castle guard" item="slingshot_shells">
      <en><![CDATA[Shoot #item# at #noun#]]></en>
      <de><![CDATA[]]></de>
      <fr><![CDATA[]]></fr>
      <it><![CDATA[]]></it>
      <ru><![CDATA[#item#: выстрелить в цель (#noun#)]]></ru>
      <es><![CDATA[]]></es>
    </c42>
    <c46 noun="Nigel Trelawney" item="slingshot_shells">
      <en><![CDATA[Shoot #item# at #noun#]]></en>
      <de><![CDATA[]]></de>
      <fr><![CDATA[]]></fr>
      <it><![CDATA[]]></it>
      <ru><![CDATA[#item#: выстрелить в цель (#noun#)]]></ru>
      <es><![CDATA[]]></es>
    </c46>
    <c50 noun="Lowell Cain" item="slingshot_shells">
      <en><![CDATA[Shoot #item# at #noun#]]></en>
      <de><![CDATA[]]></de>
      <fr><![CDATA[]]></fr>
      <it><![CDATA[]]></it>
      <ru><![CDATA[#item#: выстрелить в цель (#noun#)]]></ru>
      <es><![CDATA[]]></es>
    </c50>
  </c>
  <DIALOGUE><![CDATA[
		Dialogue subtitles deliver game narrative and player discussion.
		 Each dialogue subtitle includes an associated sound file that should be recorded and grouped by language.
]]></DIALOGUE>
  <d>
    <d0 puppet="_avatar" sound="boathouse3_riftwindow0000.mp3">
      <en><![CDATA[That’s McManus’ boat. Grandpa hired him to bring us to his nearby laboratory to fix my heart.]]></en>
      <de><![CDATA[]]></de>
      <fr><![CDATA[]]></fr>
      <it><![CDATA[]]></it>
      <ru><![CDATA[Это лодка Макмануса. Дедушка нанял его, чтобы доставить нас в лабораторию и вылечить мне сердце.]]></ru>
      <es><![CDATA[]]></es>
    </d0>
    <d1 puppet="_avatar" sound="boathouse3_riftwindow0001.mp3">
      <en><![CDATA[Unfortunately Vincent was waiting for us there. He stole the boat and took me here to Ravenhollow where his henchmen had already been waiting for us.]]></en>
      <de><![CDATA[]]></de>
      <fr><![CDATA[]]></fr>
      <it><![CDATA[]]></it>
      <ru><![CDATA[К несчастью, там нас поджидал Винсент. Он украл лодку и привез меня сюда, в Рэйвенхоллоу, где его подручные уже готовились к нашему прибытию.]]></ru>
      <es><![CDATA[]]></es>
    </d1>
    <d2 puppet="_avatar" sound="boathouse3_riftwindow0002.mp3">
      <en><![CDATA[I guess Vincent knew grandpa and the others would follow us here ... they walked right into his trap.]]></en>
      <de><![CDATA[]]></de>
      <fr><![CDATA[]]></fr>
      <it><![CDATA[]]></it>
      <ru><![CDATA[Наверное, Винсент знал, что дедушка и остальные последуют за нами... И они угодили прямиком в ловушку.]]></ru>
      <es><![CDATA[]]></es>
    </d2>
    <d3 puppet="nigel" sound="boathouse3_riftwindow0003.mp3">
      <en><![CDATA[This door leads into the lighthouse.]]></en>
      <de><![CDATA[]]></de>
      <fr><![CDATA[]]></fr>
      <it><![CDATA[]]></it>
      <ru><![CDATA[Эта дверь ведет в маяк.]]></ru>
      <es><![CDATA[]]></es>
    </d3>
    <d4 puppet="_avatar" sound="boathouse3_riftwindow0004.mp3">
      <en><![CDATA[Is anyone in there?]]></en>
      <de><![CDATA[]]></de>
      <fr><![CDATA[]]></fr>
      <it><![CDATA[]]></it>
      <ru><![CDATA[Есть кто живой?]]></ru>
      <es><![CDATA[]]></es>
    </d4>
    <d5 puppet="_avatar" sound="boathouse3_riftwindow0005.mp3">
      <en><![CDATA[Hello?]]></en>
      <de><![CDATA[]]></de>
      <fr><![CDATA[]]></fr>
      <it><![CDATA[]]></it>
      <ru><![CDATA[Эй!]]></ru>
      <es><![CDATA[]]></es>
    </d5>
    <d6 puppet="_avatar" sound="boathouse3_riftwindow0006.mp3">
      <en><![CDATA[I don’t think there’s anyone inside the lighthouse.]]></en>
      <de><![CDATA[]]></de>
      <fr><![CDATA[]]></fr>
      <it><![CDATA[]]></it>
      <ru><![CDATA[Судя по всему, на маяке никого нет.]]></ru>
      <es><![CDATA[]]></es>
    </d6>
    <d7 puppet="_avatar" sound="boathouse3_riftwindow0007.mp3">
      <en><![CDATA[The lighthouse door is locked. What a surprise.]]></en>
      <de><![CDATA[]]></de>
      <fr><![CDATA[]]></fr>
      <it><![CDATA[]]></it>
      <ru><![CDATA[Дверь в маяк заперта. Какой сюрприз.]]></ru>
      <es><![CDATA[]]></es>
    </d7>
    <d8 puppet="_avatar" sound="boathouse3_riftwindow0008.mp3">
      <en><![CDATA[I still haven’t seen a lot of Ravenhollow. I heard it’s worth a visit, though.]]></en>
      <de><![CDATA[]]></de>
      <fr><![CDATA[]]></fr>
      <it><![CDATA[]]></it>
      <ru><![CDATA[Мне толком и не удалось увидеть Рэйвенхоллоу. Говорят, однако, здесь есть на что посмотреть.]]></ru>
      <es><![CDATA[]]></es>
    </d8>
    <d9 puppet="_avatar" sound="boathouse3_riftwindow0009.mp3">
      <en><![CDATA[I have to be careful not to attract too much attention!]]></en>
      <de><![CDATA[]]></de>
      <fr><![CDATA[]]></fr>
      <it><![CDATA[]]></it>
      <ru><![CDATA[Надо быть осторожнее и не привлекать к себе внимания!]]></ru>
      <es><![CDATA[]]></es>
    </d9>
    <d10 puppet="_avatar" sound="boathouse3_riftwindow0010.mp3">
      <en><![CDATA[I would like to, but being locked up in here doesn’t really help me to stride through that gate.]]></en>
      <de><![CDATA[]]></de>
      <fr><![CDATA[]]></fr>
      <it><![CDATA[]]></it>
      <ru><![CDATA[Я бы с радостью, но, сидя здесь взаперти, я вряд ли смогу пройти через ворота.]]></ru>
      <es><![CDATA[]]></es>
    </d10>
    <d11 puppet="nigel" sound="boathouse3_riftwindow0011.mp3">
      <en><![CDATA[It seems the boat had been patched already before it was finally damaged like this.]]></en>
      <de><![CDATA[]]></de>
      <fr><![CDATA[]]></fr>
      <it><![CDATA[]]></it>
      <ru><![CDATA[Похоже, лодку подлатали еще до того, как она пришла в такое состояние.]]></ru>
      <es><![CDATA[]]></es>
    </d11>
    <d12 puppet="_avatar" sound="boathouse3_riftwindow0012.mp3">
      <en><![CDATA[Let’s see if I can break this patch lose...]]></en>
      <de><![CDATA[]]></de>
      <fr><![CDATA[]]></fr>
      <it><![CDATA[]]></it>
      <ru><![CDATA[Посмотрим, смогу ли я пробить эту заплатку...]]></ru>
      <es><![CDATA[]]></es>
    </d12>
    <d13 puppet="_avatar" sound="boathouse3_riftwindow0013.mp3">
      <en><![CDATA[Well, that was easier than I expected.]]></en>
      <de><![CDATA[]]></de>
      <fr><![CDATA[]]></fr>
      <it><![CDATA[]]></it>
      <ru><![CDATA[Все проще, чем казалось вначале.]]></ru>
      <es><![CDATA[]]></es>
    </d13>
    <d14 puppet="nigel" sound="boathouse3_riftwindow0014.mp3">
      <en><![CDATA[It’s a bucket filled with thick, sticky tar.]]></en>
      <de><![CDATA[]]></de>
      <fr><![CDATA[]]></fr>
      <it><![CDATA[]]></it>
      <ru><![CDATA[Это ведро, доверху заполненное смолой.]]></ru>
      <es><![CDATA[]]></es>
    </d14>
    <d15 puppet="_avatar" sound="boathouse3_riftwindow0015.mp3">
      <en><![CDATA[A bucket o’ tar might come in handy.]]></en>
      <de><![CDATA[]]></de>
      <fr><![CDATA[]]></fr>
      <it><![CDATA[]]></it>
      <ru><![CDATA[Ведро смолы вполне может пригодиться.]]></ru>
      <es><![CDATA[]]></es>
    </d15>
    <d16 puppet="_avatar" sound="boathouse3_riftwindow0016.mp3">
      <en><![CDATA[Useless.]]></en>
      <de><![CDATA[]]></de>
      <fr><![CDATA[]]></fr>
      <it><![CDATA[]]></it>
      <ru><![CDATA[Бесполезно.]]></ru>
      <es><![CDATA[]]></es>
    </d16>
    <d17 puppet="_avatar" sound="boathouse3_riftwindow0017.mp3">
      <en><![CDATA[The walls are too stable. I have to find another way to escape from this boathouse.]]></en>
      <de><![CDATA[]]></de>
      <fr><![CDATA[]]></fr>
      <it><![CDATA[]]></it>
      <ru><![CDATA[Стены слишком крепкие. Надо найти другой способ сбежать из сарая.]]></ru>
      <es><![CDATA[]]></es>
    </d17>
    <d18 puppet="_avatar" sound="boathouse3_riftwindow0018.mp3">
      <en><![CDATA[I’m glad Mr. McManus is alright ... the last time I saw him, Vincent threw him overboard.]]></en>
      <de><![CDATA[]]></de>
      <fr><![CDATA[]]></fr>
      <it><![CDATA[]]></it>
      <ru><![CDATA[Хорошо, что мистер Макманус в порядке... В последнюю нашу встречу Винсент вышвырнул его за борт.]]></ru>
      <es><![CDATA[]]></es>
    </d18>
    <d19 puppet="_avatar" sound="boathouse3_riftwindow0019.mp3">
      <en><![CDATA[No ... I can’t let them know I’m here.]]></en>
      <de><![CDATA[]]></de>
      <fr><![CDATA[]]></fr>
      <it><![CDATA[]]></it>
      <ru><![CDATA[Нет... Нельзя выдавать свое присутствие.]]></ru>
      <es><![CDATA[]]></es>
    </d19>
    <d20 puppet="_avatar" sound="boathouse3_riftwindow0020.mp3">
      <en><![CDATA[No, McManus has always seemed like such a nice man. He doesn’t deserve to be shot at.]]></en>
      <de><![CDATA[]]></de>
      <fr><![CDATA[]]></fr>
      <it><![CDATA[]]></it>
      <ru><![CDATA[Нет, Макманус всегда казался таким славным. Не надо в него стрелять, он не заслужил.]]></ru>
      <es><![CDATA[]]></es>
    </d20>
    <d21 puppet="_avatar" sound="boathouse3_riftwindow0021.mp3">
      <en><![CDATA[I have never seen him so worried.]]></en>
      <de><![CDATA[]]></de>
      <fr><![CDATA[]]></fr>
      <it><![CDATA[]]></it>
      <ru><![CDATA[Не приходилось видеть его таким обеспокоенным.]]></ru>
      <es><![CDATA[]]></es>
    </d21>
    <d22 puppet="_avatar" sound="boathouse3_riftwindow0022.mp3">
      <en><![CDATA[Grandpa always did the best he could to protect me ... he never told me a word about Vincent and what had happened at the Smith Institute.]]></en>
      <de><![CDATA[]]></de>
      <fr><![CDATA[]]></fr>
      <it><![CDATA[]]></it>
      <ru><![CDATA[Дедушка всегда старался защитить меня... Ни слова не сказал о Винсенте и о том, что случилось в институте Смита.]]></ru>
      <es><![CDATA[]]></es>
    </d22>
    <d23 puppet="_avatar" sound="boathouse3_riftwindow0023.mp3">
      <en><![CDATA[No, I can’t let him know I’m here. It might cause a paradox!]]></en>
      <de><![CDATA[]]></de>
      <fr><![CDATA[]]></fr>
      <it><![CDATA[]]></it>
      <ru><![CDATA[Нет, нельзя себя выдавать. Это может вызвать парадокс!]]></ru>
      <es><![CDATA[]]></es>
    </d23>
    <d24 puppet="_avatar" sound="boathouse3_riftwindow0024.mp3">
      <en><![CDATA[Or he’d just get VERY confused.]]></en>
      <de><![CDATA[]]></de>
      <fr><![CDATA[]]></fr>
      <it><![CDATA[]]></it>
      <ru><![CDATA[Ну, или он очень сильно удивится.]]></ru>
      <es><![CDATA[]]></es>
    </d24>
    <d25 puppet="_avatar" sound="boathouse3_riftwindow0025.mp3">
      <en><![CDATA[What? No, I wouldn’t even consider shooting at Grandpa.]]></en>
      <de><![CDATA[]]></de>
      <fr><![CDATA[]]></fr>
      <it><![CDATA[]]></it>
      <ru><![CDATA[Что? Нет, в дедушку я стрелять не стану.]]></ru>
      <es><![CDATA[]]></es>
    </d25>
    <d26 puppet="_avatar" sound="boathouse3_riftwindow0026.mp3">
      <en><![CDATA[Even good old Shroomy doesn’t like Lowell Cain.]]></en>
      <de><![CDATA[]]></de>
      <fr><![CDATA[]]></fr>
      <it><![CDATA[]]></it>
      <ru><![CDATA[Даже старина Грибок не любит Лоуэлла Кейна.]]></ru>
      <es><![CDATA[]]></es>
    </d26>
    <d27 puppet="_avatar" sound="boathouse3_riftwindow0027.mp3">
      <en><![CDATA[That would attract the attention of the others.]]></en>
      <de><![CDATA[]]></de>
      <fr><![CDATA[]]></fr>
      <it><![CDATA[]]></it>
      <ru><![CDATA[Это может привлечь внимание других.]]></ru>
      <es><![CDATA[]]></es>
    </d27>
    <d28 puppet="_avatar" sound="boathouse3_riftwindow0028.mp3">
      <en><![CDATA[I take issue with being abusive to animals.]]></en>
      <de><![CDATA[]]></de>
      <fr><![CDATA[]]></fr>
      <it><![CDATA[]]></it>
      <ru><![CDATA[Не люблю тех, кто обижает животных.]]></ru>
      <es><![CDATA[]]></es>
    </d28>
    <d29 puppet="_avatar" sound="boathouse3_riftwindow0029.mp3">
      <en><![CDATA[Hey, there is something sticking out from that barrel.]]></en>
      <de><![CDATA[]]></de>
      <fr><![CDATA[]]></fr>
      <it><![CDATA[]]></it>
      <ru><![CDATA[Ого, из этой бочки что-то торчит.]]></ru>
      <es><![CDATA[]]></es>
    </d29>
    <d30 puppet="_avatar" sound="boathouse3_riftwindow0030.mp3">
      <en><![CDATA[If I stretch my arm out as far as I can I might be able to ...]]></en>
      <de><![CDATA[]]></de>
      <fr><![CDATA[]]></fr>
      <it><![CDATA[]]></it>
      <ru><![CDATA[Если я протяну руку как можно дальше, то, может быть, и сумею...]]></ru>
      <es><![CDATA[]]></es>
    </d30>
    <d31 puppet="_avatar" sound="boathouse3_riftwindow0031.mp3">
      <en><![CDATA[Yes! I got it!]]></en>
      <de><![CDATA[]]></de>
      <fr><![CDATA[]]></fr>
      <it><![CDATA[]]></it>
      <ru><![CDATA[Есть! Достал!]]></ru>
      <es><![CDATA[]]></es>
    </d31>
    <d32 puppet="_avatar" sound="boathouse3_riftwindow0032.mp3">
      <en><![CDATA[Hey, it’s a slingshot!]]></en>
      <de><![CDATA[]]></de>
      <fr><![CDATA[]]></fr>
      <it><![CDATA[]]></it>
      <ru><![CDATA[Да это же рогатка!]]></ru>
      <es><![CDATA[]]></es>
    </d32>
    <d33 puppet="_avatar" sound="boathouse3_riftwindow0033.mp3">
      <en><![CDATA[I wonder if this slingshot is in any way connected to that hulking Castle guard being hit on the back of the head.]]></en>
      <de><![CDATA[]]></de>
      <fr><![CDATA[]]></fr>
      <it><![CDATA[]]></it>
      <ru><![CDATA[Интересно, эта рогатка как-то связана с бугаем-охранником, получившим по затылку?]]></ru>
      <es><![CDATA[]]></es>
    </d33>
    <d34 puppet="_avatar" sound="boathouse3_riftwindow0034.mp3">
      <en><![CDATA[Hey, there is something sticking out from that barrel.]]></en>
      <de><![CDATA[]]></de>
      <fr><![CDATA[]]></fr>
      <it><![CDATA[]]></it>
      <ru><![CDATA[Ого, из этой бочки что-то торчит.]]></ru>
      <es><![CDATA[]]></es>
    </d34>
    <d35 puppet="_avatar" sound="boathouse3_riftwindow0035.mp3">
      <en><![CDATA[If I stretch my arm out as far as I can I might be able to ...]]></en>
      <de><![CDATA[]]></de>
      <fr><![CDATA[]]></fr>
      <it><![CDATA[]]></it>
      <ru><![CDATA[Если я протяну руку как можно дальше, то, может быть, и сумею...]]></ru>
      <es><![CDATA[]]></es>
    </d35>
    <d36 puppet="_avatar" sound="boathouse3_riftwindow0036.mp3">
      <en><![CDATA[Yes! I got it!]]></en>
      <de><![CDATA[]]></de>
      <fr><![CDATA[]]></fr>
      <it><![CDATA[]]></it>
      <ru><![CDATA[Есть! Достал!]]></ru>
      <es><![CDATA[]]></es>
    </d36>
    <d37 puppet="_avatar" sound="boathouse3_riftwindow0037.mp3">
      <en><![CDATA[Hey, it’s a slingshot!]]></en>
      <de><![CDATA[]]></de>
      <fr><![CDATA[]]></fr>
      <it><![CDATA[]]></it>
      <ru><![CDATA[Да это же рогатка!]]></ru>
      <es><![CDATA[]]></es>
    </d37>
    <d38 puppet="_avatar" sound="boathouse3_riftwindow0038.mp3">
      <en><![CDATA[I wonder if this slingshot is in any way connected to that hulking Castle guard being hit on the back of the head.]]></en>
      <de><![CDATA[]]></de>
      <fr><![CDATA[]]></fr>
      <it><![CDATA[]]></it>
      <ru><![CDATA[Интересно, эта рогатка как-то связана с бугаем-охранником, получившим по затылку?]]></ru>
      <es><![CDATA[]]></es>
    </d38>
    <d39 puppet="_avatar" sound="boathouse3_riftwindow0039.mp3">
      <en><![CDATA[I hate that guy.]]></en>
      <de><![CDATA[]]></de>
      <fr><![CDATA[]]></fr>
      <it><![CDATA[]]></it>
      <ru><![CDATA[Ненавижу этого типа.]]></ru>
      <es><![CDATA[]]></es>
    </d39>
    <d40 puppet="_avatar" sound="boathouse3_riftwindow0040.mp3">
      <en><![CDATA[It looks like he’s about to arrest grandpa and the others ... I have to find a way to stop them from taking Nigel up to the castle as well.]]></en>
      <de><![CDATA[]]></de>
      <fr><![CDATA[]]></fr>
      <it><![CDATA[]]></it>
      <ru><![CDATA[Похоже, он собирается арестовать дедушку и остальных... Надо придумать, как не дать им забрать в замок и Найджела тоже.]]></ru>
      <es><![CDATA[]]></es>
    </d40>
    <d41 puppet="_avatar" sound="boathouse3_riftwindow0041.mp3">
      <en><![CDATA[No ... I can’t let anyone except Nigel know that I’m here.]]></en>
      <de><![CDATA[]]></de>
      <fr><![CDATA[]]></fr>
      <it><![CDATA[]]></it>
      <ru><![CDATA[Нет... Никто, кроме Найджела, не должен знать, что я здесь.]]></ru>
      <es><![CDATA[]]></es>
    </d41>
    <d42 puppet="_avatar" sound="boathouse3_riftwindow0042.mp3">
      <en><![CDATA[Maybe I can make that bug guy lose his temper and lock Nigel up with me in the boathouse ...]]></en>
      <de><![CDATA[]]></de>
      <fr><![CDATA[]]></fr>
      <it><![CDATA[]]></it>
      <ru><![CDATA[Может, я смогу вывести из себя этого громилу, чтобы он запер Найджела вместе со мной в лодочном сарае?..]]></ru>
      <es><![CDATA[]]></es>
    </d42>
    <d43 puppet="_avatar" sound="boathouse3_riftwindow0043.mp3">
      <en><![CDATA[I think he believes Nigel hit him.]]></en>
      <de><![CDATA[]]></de>
      <fr><![CDATA[]]></fr>
      <it><![CDATA[]]></it>
      <ru><![CDATA[Думаю, он поверил, что это Найджел его стукнул.]]></ru>
      <es><![CDATA[]]></es>
    </d43>
    <d44 puppet="_avatar" sound="boathouse3_riftwindow0044.mp3">
      <en><![CDATA[One more hit should drive the guard over the edge.]]></en>
      <de><![CDATA[]]></de>
      <fr><![CDATA[]]></fr>
      <it><![CDATA[]]></it>
      <ru><![CDATA[Еще один удар, и охранник точно взбесится.]]></ru>
      <es><![CDATA[]]></es>
    </d44>
    <d45 puppet="_avatar" sound="boathouse3_riftwindow0045.mp3">
      <en><![CDATA[Ouch!]]></en>
      <de><![CDATA[]]></de>
      <fr><![CDATA[]]></fr>
      <it><![CDATA[]]></it>
      <ru><![CDATA[Ой!]]></ru>
      <es><![CDATA[]]></es>
    </d45>
    <d46 puppet="_avatar" sound="boathouse3_riftwindow0046.mp3">
      <en><![CDATA[Sorry, Nigel! I didn’t expect that he’d be THAT brutal!]]></en>
      <de><![CDATA[]]></de>
      <fr><![CDATA[]]></fr>
      <it><![CDATA[]]></it>
      <ru><![CDATA[Извини, Найджел! Я не думала, что он настолько взбесится!]]></ru>
      <es><![CDATA[]]></es>
    </d46>
    <d47 puppet="_avatar" sound="boathouse3_riftwindow0047.mp3">
      <en><![CDATA[I’d better get rid of the slingshot before they bring Nigel in here ...]]></en>
      <de><![CDATA[]]></de>
      <fr><![CDATA[]]></fr>
      <it><![CDATA[]]></it>
      <ru><![CDATA[Лучше избавиться от рогатки, пока сюда не привели Найджела...]]></ru>
      <es><![CDATA[]]></es>
    </d47>
    <d48 puppet="_avatar" sound="boathouse3_riftwindow0048.mp3">
      <en><![CDATA[That’s the one I’m looking for ... Nigel Trelawney.]]></en>
      <de><![CDATA[]]></de>
      <fr><![CDATA[]]></fr>
      <it><![CDATA[]]></it>
      <ru><![CDATA[Вот его-то мне и надо... Найджел Трелони.]]></ru>
      <es><![CDATA[]]></es>
    </d48>
    <d49 puppet="_avatar" sound="boathouse3_riftwindow0049.mp3">
      <en><![CDATA[I just saw him for a brief moment when he and Nathan burst into the castle tower.]]></en>
      <de><![CDATA[]]></de>
      <fr><![CDATA[]]></fr>
      <it><![CDATA[]]></it>
      <ru><![CDATA[Я видела его всего минуту, когда они с Натаном вломились в башню замка.]]></ru>
      <es><![CDATA[]]></es>
    </d49>
    <d50 puppet="_avatar" sound="boathouse3_riftwindow0050.mp3">
      <en><![CDATA[I can’t let Cain and his henchman arrest Nigel. I have to bring his father’s picture back to the future!]]></en>
      <de><![CDATA[]]></de>
      <fr><![CDATA[]]></fr>
      <it><![CDATA[]]></it>
      <ru><![CDATA[Нельзя, чтобы Кейн и его подручные схватили Найджела. Надо отправить фотографию его отца обратно в будущее!]]></ru>
      <es><![CDATA[]]></es>
    </d50>
    <d51 puppet="_avatar" sound="boathouse3_riftwindow0051.mp3">
      <en><![CDATA[Shooting at the man that I’m trying to talk to doesn’t seem like the best way to start a conversation.]]></en>
      <de><![CDATA[]]></de>
      <fr><![CDATA[]]></fr>
      <it><![CDATA[]]></it>
      <ru><![CDATA[Стрелять в человека, с которым я хочу поговорить, не вылядит лучшим началом беседы.]]></ru>
      <es><![CDATA[]]></es>
    </d51>
    <d52 puppet="_avatar" sound="boathouse3_riftwindow0052.mp3">
      <en><![CDATA[Lowell Cain ... what a schmuck.]]></en>
      <de><![CDATA[]]></de>
      <fr><![CDATA[]]></fr>
      <it><![CDATA[]]></it>
      <ru><![CDATA[Лоуэлл Кейн... Ну и козел.]]></ru>
      <es><![CDATA[]]></es>
    </d52>
    <d53 puppet="_avatar" sound="boathouse3_riftwindow0053.mp3">
      <en><![CDATA[I overheard a conversation between two of his henchmen ... they said Cain was given a dishonorable discharge from the army.]]></en>
      <de><![CDATA[]]></de>
      <fr><![CDATA[]]></fr>
      <it><![CDATA[]]></it>
      <ru><![CDATA[Мне удалось подслушать разговор двух его подручных... Они говорили, что Кейна с позором выгнали из армии.]]></ru>
      <es><![CDATA[]]></es>
    </d53>
    <d54 puppet="_avatar" sound="boathouse3_riftwindow0054.mp3">
      <en><![CDATA[He really thought that he could cooperate and even profit from a madman like Vincent and build up his own regime.]]></en>
      <de><![CDATA[]]></de>
      <fr><![CDATA[]]></fr>
      <it><![CDATA[]]></it>
      <ru><![CDATA[Он и вправду думал, что сможет получить пользу от сотрудничества с безумцем типа Винсента и править городом.]]></ru>
      <es><![CDATA[]]></es>
    </d54>
    <d55 puppet="_avatar" sound="boathouse3_riftwindow0055.mp3">
      <en><![CDATA[Even if I could I’d prefer not to.]]></en>
      <de><![CDATA[]]></de>
      <fr><![CDATA[]]></fr>
      <it><![CDATA[]]></it>
      <ru><![CDATA[Даже если было бы можно, лучше не надо.]]></ru>
      <es><![CDATA[]]></es>
    </d55>
    <d56 puppet="_avatar" sound="boathouse3_riftwindow0056.mp3">
      <en><![CDATA[That big guy is standing in the way.]]></en>
      <de><![CDATA[]]></de>
      <fr><![CDATA[]]></fr>
      <it><![CDATA[]]></it>
      <ru><![CDATA[Этот громила загораживает дорогу.]]></ru>
      <es><![CDATA[]]></es>
    </d56>
  </d>
</localize>