<localize>
  <NOUNS><![CDATA[
		Nouns state the title of an object that the player can mouse-over and interact with.
		These are generally singular nouns.
		Nouns may be blank.
]]></NOUNS>
  <n>
    <n0>
      <en><![CDATA[]]></en>
      <de><![CDATA[]]></de>
      <fr><![CDATA[]]></fr>
      <it><![CDATA[]]></it>
      <ru><![CDATA[]]></ru>
      <es><![CDATA[]]></es>
    </n0>
    <n1>
      <en><![CDATA[]]></en>
      <de><![CDATA[]]></de>
      <fr><![CDATA[]]></fr>
      <it><![CDATA[]]></it>
      <ru><![CDATA[]]></ru>
      <es><![CDATA[]]></es>
    </n1>
    <n2>
      <en><![CDATA[]]></en>
      <de><![CDATA[]]></de>
      <fr><![CDATA[]]></fr>
      <it><![CDATA[]]></it>
      <ru><![CDATA[]]></ru>
      <es><![CDATA[]]></es>
    </n2>
    <n3>
      <en><![CDATA[]]></en>
      <de><![CDATA[]]></de>
      <fr><![CDATA[]]></fr>
      <it><![CDATA[]]></it>
      <ru><![CDATA[]]></ru>
      <es><![CDATA[]]></es>
    </n3>
    <n4>
      <en><![CDATA[]]></en>
      <de><![CDATA[]]></de>
      <fr><![CDATA[]]></fr>
      <it><![CDATA[]]></it>
      <ru><![CDATA[]]></ru>
      <es><![CDATA[]]></es>
    </n4>
    <n5>
      <en><![CDATA[]]></en>
      <de><![CDATA[]]></de>
      <fr><![CDATA[]]></fr>
      <it><![CDATA[]]></it>
      <ru><![CDATA[]]></ru>
      <es><![CDATA[]]></es>
    </n5>
    <n6>
      <en><![CDATA[]]></en>
      <de><![CDATA[]]></de>
      <fr><![CDATA[]]></fr>
      <it><![CDATA[]]></it>
      <ru><![CDATA[]]></ru>
      <es><![CDATA[]]></es>
    </n6>
    <n7>
      <en><![CDATA[]]></en>
      <de><![CDATA[]]></de>
      <fr><![CDATA[]]></fr>
      <it><![CDATA[]]></it>
      <ru><![CDATA[]]></ru>
      <es><![CDATA[]]></es>
    </n7>
    <n8>
      <en><![CDATA[]]></en>
      <de><![CDATA[]]></de>
      <fr><![CDATA[]]></fr>
      <it><![CDATA[]]></it>
      <ru><![CDATA[]]></ru>
      <es><![CDATA[]]></es>
    </n8>
    <n9>
      <en><![CDATA[]]></en>
      <de><![CDATA[]]></de>
      <fr><![CDATA[]]></fr>
      <it><![CDATA[]]></it>
      <ru><![CDATA[]]></ru>
      <es><![CDATA[]]></es>
    </n9>
    <n10>
      <en><![CDATA[]]></en>
      <de><![CDATA[]]></de>
      <fr><![CDATA[]]></fr>
      <it><![CDATA[]]></it>
      <ru><![CDATA[]]></ru>
      <es><![CDATA[]]></es>
    </n10>
    <n11>
      <en><![CDATA[Professor Smith]]></en>
      <de><![CDATA[]]></de>
      <fr><![CDATA[]]></fr>
      <it><![CDATA[]]></it>
      <ru><![CDATA[Профессор Смит]]></ru>
      <es><![CDATA[]]></es>
    </n11>
    <n12>
      <en><![CDATA[Professor Smith]]></en>
      <de><![CDATA[]]></de>
      <fr><![CDATA[]]></fr>
      <it><![CDATA[]]></it>
      <ru><![CDATA[Профессор Смит]]></ru>
      <es><![CDATA[]]></es>
    </n12>
    <n13>
      <en><![CDATA[Professor Smith]]></en>
      <de><![CDATA[]]></de>
      <fr><![CDATA[]]></fr>
      <it><![CDATA[]]></it>
      <ru><![CDATA[Профессор Смит]]></ru>
      <es><![CDATA[]]></es>
    </n13>
    <n14>
      <en><![CDATA[Nigel]]></en>
      <de><![CDATA[]]></de>
      <fr><![CDATA[]]></fr>
      <it><![CDATA[]]></it>
      <ru><![CDATA[Найджел]]></ru>
      <es><![CDATA[]]></es>
    </n14>
    <n15>
      <en><![CDATA[Nigel]]></en>
      <de><![CDATA[]]></de>
      <fr><![CDATA[]]></fr>
      <it><![CDATA[]]></it>
      <ru><![CDATA[Найджел]]></ru>
      <es><![CDATA[]]></es>
    </n15>
    <n16>
      <en><![CDATA[]]></en>
      <de><![CDATA[]]></de>
      <fr><![CDATA[]]></fr>
      <it><![CDATA[]]></it>
      <ru><![CDATA[]]></ru>
      <es><![CDATA[]]></es>
    </n16>
    <n17>
      <en><![CDATA[]]></en>
      <de><![CDATA[]]></de>
      <fr><![CDATA[]]></fr>
      <it><![CDATA[]]></it>
      <ru><![CDATA[]]></ru>
      <es><![CDATA[]]></es>
    </n17>
    <n18>
      <en><![CDATA[]]></en>
      <de><![CDATA[]]></de>
      <fr><![CDATA[]]></fr>
      <it><![CDATA[]]></it>
      <ru><![CDATA[]]></ru>
      <es><![CDATA[]]></es>
    </n18>
    <n19>
      <en><![CDATA[]]></en>
      <de><![CDATA[]]></de>
      <fr><![CDATA[]]></fr>
      <it><![CDATA[]]></it>
      <ru><![CDATA[]]></ru>
      <es><![CDATA[]]></es>
    </n19>
    <n20>
      <en><![CDATA[]]></en>
      <de><![CDATA[]]></de>
      <fr><![CDATA[]]></fr>
      <it><![CDATA[]]></it>
      <ru><![CDATA[]]></ru>
      <es><![CDATA[]]></es>
    </n20>
    <n21>
      <en><![CDATA[]]></en>
      <de><![CDATA[]]></de>
      <fr><![CDATA[]]></fr>
      <it><![CDATA[]]></it>
      <ru><![CDATA[]]></ru>
      <es><![CDATA[]]></es>
    </n21>
    <n22>
      <en><![CDATA[]]></en>
      <de><![CDATA[]]></de>
      <fr><![CDATA[]]></fr>
      <it><![CDATA[]]></it>
      <ru><![CDATA[]]></ru>
      <es><![CDATA[]]></es>
    </n22>
    <n23>
      <en><![CDATA[]]></en>
      <de><![CDATA[]]></de>
      <fr><![CDATA[]]></fr>
      <it><![CDATA[]]></it>
      <ru><![CDATA[]]></ru>
      <es><![CDATA[]]></es>
    </n23>
    <n24>
      <en><![CDATA[]]></en>
      <de><![CDATA[]]></de>
      <fr><![CDATA[]]></fr>
      <it><![CDATA[]]></it>
      <ru><![CDATA[]]></ru>
      <es><![CDATA[]]></es>
    </n24>
    <n25>
      <en><![CDATA[]]></en>
      <de><![CDATA[]]></de>
      <fr><![CDATA[]]></fr>
      <it><![CDATA[]]></it>
      <ru><![CDATA[]]></ru>
      <es><![CDATA[]]></es>
    </n25>
    <n26>
      <en><![CDATA[]]></en>
      <de><![CDATA[]]></de>
      <fr><![CDATA[]]></fr>
      <it><![CDATA[]]></it>
      <ru><![CDATA[]]></ru>
      <es><![CDATA[]]></es>
    </n26>
    <n27>
      <en><![CDATA[]]></en>
      <de><![CDATA[]]></de>
      <fr><![CDATA[]]></fr>
      <it><![CDATA[]]></it>
      <ru><![CDATA[]]></ru>
      <es><![CDATA[]]></es>
    </n27>
    <n28>
      <en><![CDATA[nigel]]></en>
      <de><![CDATA[]]></de>
      <fr><![CDATA[]]></fr>
      <it><![CDATA[]]></it>
      <ru><![CDATA[Найджел]]></ru>
      <es><![CDATA[]]></es>
    </n28>
    <n29>
      <en><![CDATA[]]></en>
      <de><![CDATA[]]></de>
      <fr><![CDATA[]]></fr>
      <it><![CDATA[]]></it>
      <ru><![CDATA[]]></ru>
      <es><![CDATA[]]></es>
    </n29>
    <n30>
      <en><![CDATA[]]></en>
      <de><![CDATA[]]></de>
      <fr><![CDATA[]]></fr>
      <it><![CDATA[]]></it>
      <ru><![CDATA[]]></ru>
      <es><![CDATA[]]></es>
    </n30>
    <n31>
      <en><![CDATA[Time Rift Apparatus]]></en>
      <de><![CDATA[]]></de>
      <fr><![CDATA[]]></fr>
      <it><![CDATA[]]></it>
      <ru><![CDATA[Генератор временного разрыва]]></ru>
      <es><![CDATA[]]></es>
    </n31>
    <n32>
      <en><![CDATA[Vincent]]></en>
      <de><![CDATA[]]></de>
      <fr><![CDATA[]]></fr>
      <it><![CDATA[]]></it>
      <ru><![CDATA[Винсент]]></ru>
      <es><![CDATA[]]></es>
    </n32>
    <n33>
      <en><![CDATA[Prof. Smith]]></en>
      <de><![CDATA[]]></de>
      <fr><![CDATA[]]></fr>
      <it><![CDATA[]]></it>
      <ru><![CDATA[Проф. Смит]]></ru>
      <es><![CDATA[]]></es>
    </n33>
    <n34>
      <en><![CDATA[Nigel]]></en>
      <de><![CDATA[]]></de>
      <fr><![CDATA[]]></fr>
      <it><![CDATA[]]></it>
      <ru><![CDATA[Найджел]]></ru>
      <es><![CDATA[]]></es>
    </n34>
    <n35>
      <en><![CDATA[]]></en>
      <de><![CDATA[]]></de>
      <fr><![CDATA[]]></fr>
      <it><![CDATA[]]></it>
      <ru><![CDATA[]]></ru>
      <es><![CDATA[]]></es>
    </n35>
    <n36>
      <en><![CDATA[]]></en>
      <de><![CDATA[]]></de>
      <fr><![CDATA[]]></fr>
      <it><![CDATA[]]></it>
      <ru><![CDATA[]]></ru>
      <es><![CDATA[]]></es>
    </n36>
    <n37>
      <en><![CDATA[]]></en>
      <de><![CDATA[]]></de>
      <fr><![CDATA[]]></fr>
      <it><![CDATA[]]></it>
      <ru><![CDATA[]]></ru>
      <es><![CDATA[]]></es>
    </n37>
  </n>
  <VERBS><![CDATA[
		A verb summary describes an interaction that the player can perform on an object.
		Formatting of the verb/noun wording is controlled globally through the verb dialect field.
		Global verb dialect allows you to specify a "#verb# #noun#" formatting string that will govern how all verbs and nouns are joined together.
]]></VERBS>
  <v>
    <v0 noun="">
      <en><![CDATA[Look at]]></en>
      <de><![CDATA[]]></de>
      <fr><![CDATA[]]></fr>
      <it><![CDATA[]]></it>
      <ru><![CDATA[Осмотреть:]]></ru>
      <es><![CDATA[]]></es>
    </v0>
    <v1 noun="">
      <en><![CDATA[Talk to]]></en>
      <de><![CDATA[]]></de>
      <fr><![CDATA[]]></fr>
      <it><![CDATA[]]></it>
      <ru><![CDATA[Поговорить:]]></ru>
      <es><![CDATA[]]></es>
    </v1>
    <v2 noun="">
      <en><![CDATA[Use]]></en>
      <de><![CDATA[]]></de>
      <fr><![CDATA[]]></fr>
      <it><![CDATA[]]></it>
      <ru><![CDATA[Использовать:]]></ru>
      <es><![CDATA[]]></es>
    </v2>
    <v3 noun="">
      <en><![CDATA[Look at]]></en>
      <de><![CDATA[]]></de>
      <fr><![CDATA[]]></fr>
      <it><![CDATA[]]></it>
      <ru><![CDATA[Осмотреть:]]></ru>
      <es><![CDATA[]]></es>
    </v3>
    <v4 noun="">
      <en><![CDATA[Talk to]]></en>
      <de><![CDATA[]]></de>
      <fr><![CDATA[]]></fr>
      <it><![CDATA[]]></it>
      <ru><![CDATA[Поговорить:]]></ru>
      <es><![CDATA[]]></es>
    </v4>
    <v5 noun="">
      <en><![CDATA[Use]]></en>
      <de><![CDATA[]]></de>
      <fr><![CDATA[]]></fr>
      <it><![CDATA[]]></it>
      <ru><![CDATA[Использовать:]]></ru>
      <es><![CDATA[]]></es>
    </v5>
    <v6 noun="">
      <en><![CDATA[Look at]]></en>
      <de><![CDATA[]]></de>
      <fr><![CDATA[]]></fr>
      <it><![CDATA[]]></it>
      <ru><![CDATA[Осмотреть:]]></ru>
      <es><![CDATA[]]></es>
    </v6>
    <v7 noun="">
      <en><![CDATA[Talk to]]></en>
      <de><![CDATA[]]></de>
      <fr><![CDATA[]]></fr>
      <it><![CDATA[]]></it>
      <ru><![CDATA[Поговорить:]]></ru>
      <es><![CDATA[]]></es>
    </v7>
    <v8 noun="">
      <en><![CDATA[Use]]></en>
      <de><![CDATA[]]></de>
      <fr><![CDATA[]]></fr>
      <it><![CDATA[]]></it>
      <ru><![CDATA[Использовать:]]></ru>
      <es><![CDATA[]]></es>
    </v8>
    <v9 noun="">
      <en><![CDATA[Look at]]></en>
      <de><![CDATA[]]></de>
      <fr><![CDATA[]]></fr>
      <it><![CDATA[]]></it>
      <ru><![CDATA[Осмотреть:]]></ru>
      <es><![CDATA[]]></es>
    </v9>
    <v10 noun="">
      <en><![CDATA[Talk to]]></en>
      <de><![CDATA[]]></de>
      <fr><![CDATA[]]></fr>
      <it><![CDATA[]]></it>
      <ru><![CDATA[Поговорить:]]></ru>
      <es><![CDATA[]]></es>
    </v10>
    <v11 noun="">
      <en><![CDATA[Use]]></en>
      <de><![CDATA[]]></de>
      <fr><![CDATA[]]></fr>
      <it><![CDATA[]]></it>
      <ru><![CDATA[Использовать:]]></ru>
      <es><![CDATA[]]></es>
    </v11>
    <v12 noun="">
      <en><![CDATA[Look at]]></en>
      <de><![CDATA[]]></de>
      <fr><![CDATA[]]></fr>
      <it><![CDATA[]]></it>
      <ru><![CDATA[Осмотреть:]]></ru>
      <es><![CDATA[]]></es>
    </v12>
    <v13 noun="">
      <en><![CDATA[Talk to]]></en>
      <de><![CDATA[]]></de>
      <fr><![CDATA[]]></fr>
      <it><![CDATA[]]></it>
      <ru><![CDATA[Поговорить:]]></ru>
      <es><![CDATA[]]></es>
    </v13>
    <v14 noun="">
      <en><![CDATA[Use]]></en>
      <de><![CDATA[]]></de>
      <fr><![CDATA[]]></fr>
      <it><![CDATA[]]></it>
      <ru><![CDATA[Использовать:]]></ru>
      <es><![CDATA[]]></es>
    </v14>
    <v15 noun="">
      <en><![CDATA[Look at]]></en>
      <de><![CDATA[]]></de>
      <fr><![CDATA[]]></fr>
      <it><![CDATA[]]></it>
      <ru><![CDATA[Осмотреть:]]></ru>
      <es><![CDATA[]]></es>
    </v15>
    <v16 noun="">
      <en><![CDATA[Talk to]]></en>
      <de><![CDATA[]]></de>
      <fr><![CDATA[]]></fr>
      <it><![CDATA[]]></it>
      <ru><![CDATA[Поговорить:]]></ru>
      <es><![CDATA[]]></es>
    </v16>
    <v17 noun="">
      <en><![CDATA[Use]]></en>
      <de><![CDATA[]]></de>
      <fr><![CDATA[]]></fr>
      <it><![CDATA[]]></it>
      <ru><![CDATA[Использовать:]]></ru>
      <es><![CDATA[]]></es>
    </v17>
    <v18 noun="">
      <en><![CDATA[Look at]]></en>
      <de><![CDATA[]]></de>
      <fr><![CDATA[]]></fr>
      <it><![CDATA[]]></it>
      <ru><![CDATA[Осмотреть:]]></ru>
      <es><![CDATA[]]></es>
    </v18>
    <v19 noun="">
      <en><![CDATA[Talk to]]></en>
      <de><![CDATA[]]></de>
      <fr><![CDATA[]]></fr>
      <it><![CDATA[]]></it>
      <ru><![CDATA[Поговорить:]]></ru>
      <es><![CDATA[]]></es>
    </v19>
    <v20 noun="">
      <en><![CDATA[Use]]></en>
      <de><![CDATA[]]></de>
      <fr><![CDATA[]]></fr>
      <it><![CDATA[]]></it>
      <ru><![CDATA[Использовать:]]></ru>
      <es><![CDATA[]]></es>
    </v20>
    <v21 noun="">
      <en><![CDATA[Look at]]></en>
      <de><![CDATA[]]></de>
      <fr><![CDATA[]]></fr>
      <it><![CDATA[]]></it>
      <ru><![CDATA[Осмотреть:]]></ru>
      <es><![CDATA[]]></es>
    </v21>
    <v22 noun="">
      <en><![CDATA[Talk to]]></en>
      <de><![CDATA[]]></de>
      <fr><![CDATA[]]></fr>
      <it><![CDATA[]]></it>
      <ru><![CDATA[Поговорить:]]></ru>
      <es><![CDATA[]]></es>
    </v22>
    <v23 noun="">
      <en><![CDATA[Use]]></en>
      <de><![CDATA[]]></de>
      <fr><![CDATA[]]></fr>
      <it><![CDATA[]]></it>
      <ru><![CDATA[Использовать:]]></ru>
      <es><![CDATA[]]></es>
    </v23>
    <v24 noun="">
      <en><![CDATA[Look at]]></en>
      <de><![CDATA[]]></de>
      <fr><![CDATA[]]></fr>
      <it><![CDATA[]]></it>
      <ru><![CDATA[Осмотреть:]]></ru>
      <es><![CDATA[]]></es>
    </v24>
    <v25 noun="">
      <en><![CDATA[Talk to]]></en>
      <de><![CDATA[]]></de>
      <fr><![CDATA[]]></fr>
      <it><![CDATA[]]></it>
      <ru><![CDATA[Поговорить:]]></ru>
      <es><![CDATA[]]></es>
    </v25>
    <v26 noun="">
      <en><![CDATA[Use]]></en>
      <de><![CDATA[]]></de>
      <fr><![CDATA[]]></fr>
      <it><![CDATA[]]></it>
      <ru><![CDATA[Использовать:]]></ru>
      <es><![CDATA[]]></es>
    </v26>
    <v27 noun="Professor Smith">
      <en><![CDATA[Look at]]></en>
      <de><![CDATA[]]></de>
      <fr><![CDATA[]]></fr>
      <it><![CDATA[]]></it>
      <ru><![CDATA[Осмотреть:]]></ru>
      <es><![CDATA[]]></es>
    </v27>
    <v28 noun="Professor Smith">
      <en><![CDATA[Talk to]]></en>
      <de><![CDATA[]]></de>
      <fr><![CDATA[]]></fr>
      <it><![CDATA[]]></it>
      <ru><![CDATA[Поговорить:]]></ru>
      <es><![CDATA[]]></es>
    </v28>
    <v29 noun="Professor Smith">
      <en><![CDATA[Use]]></en>
      <de><![CDATA[]]></de>
      <fr><![CDATA[]]></fr>
      <it><![CDATA[]]></it>
      <ru><![CDATA[Использовать:]]></ru>
      <es><![CDATA[]]></es>
    </v29>
    <v30 noun="Professor Smith">
      <en><![CDATA[Look at]]></en>
      <de><![CDATA[]]></de>
      <fr><![CDATA[]]></fr>
      <it><![CDATA[]]></it>
      <ru><![CDATA[Осмотреть:]]></ru>
      <es><![CDATA[]]></es>
    </v30>
    <v31 noun="Professor Smith">
      <en><![CDATA[Talk to]]></en>
      <de><![CDATA[]]></de>
      <fr><![CDATA[]]></fr>
      <it><![CDATA[]]></it>
      <ru><![CDATA[Поговорить:]]></ru>
      <es><![CDATA[]]></es>
    </v31>
    <v32 noun="Professor Smith">
      <en><![CDATA[Use]]></en>
      <de><![CDATA[]]></de>
      <fr><![CDATA[]]></fr>
      <it><![CDATA[]]></it>
      <ru><![CDATA[Использовать:]]></ru>
      <es><![CDATA[]]></es>
    </v32>
    <v33 noun="Professor Smith">
      <en><![CDATA[Look at]]></en>
      <de><![CDATA[]]></de>
      <fr><![CDATA[]]></fr>
      <it><![CDATA[]]></it>
      <ru><![CDATA[Осмотреть:]]></ru>
      <es><![CDATA[]]></es>
    </v33>
    <v34 noun="Professor Smith">
      <en><![CDATA[Talk to]]></en>
      <de><![CDATA[]]></de>
      <fr><![CDATA[]]></fr>
      <it><![CDATA[]]></it>
      <ru><![CDATA[Поговорить:]]></ru>
      <es><![CDATA[]]></es>
    </v34>
    <v35 noun="Professor Smith">
      <en><![CDATA[Use]]></en>
      <de><![CDATA[]]></de>
      <fr><![CDATA[]]></fr>
      <it><![CDATA[]]></it>
      <ru><![CDATA[Использовать:]]></ru>
      <es><![CDATA[]]></es>
    </v35>
    <v36 noun="Nigel">
      <en><![CDATA[Look at]]></en>
      <de><![CDATA[]]></de>
      <fr><![CDATA[]]></fr>
      <it><![CDATA[]]></it>
      <ru><![CDATA[Осмотреть:]]></ru>
      <es><![CDATA[]]></es>
    </v36>
    <v37 noun="Nigel">
      <en><![CDATA[Talk to]]></en>
      <de><![CDATA[]]></de>
      <fr><![CDATA[]]></fr>
      <it><![CDATA[]]></it>
      <ru><![CDATA[Поговорить:]]></ru>
      <es><![CDATA[]]></es>
    </v37>
    <v38 noun="Nigel">
      <en><![CDATA[Use]]></en>
      <de><![CDATA[]]></de>
      <fr><![CDATA[]]></fr>
      <it><![CDATA[]]></it>
      <ru><![CDATA[Использовать:]]></ru>
      <es><![CDATA[]]></es>
    </v38>
    <v39 noun="Nigel">
      <en><![CDATA[Look at]]></en>
      <de><![CDATA[]]></de>
      <fr><![CDATA[]]></fr>
      <it><![CDATA[]]></it>
      <ru><![CDATA[Осмотреть:]]></ru>
      <es><![CDATA[]]></es>
    </v39>
    <v40 noun="Nigel">
      <en><![CDATA[Talk to]]></en>
      <de><![CDATA[]]></de>
      <fr><![CDATA[]]></fr>
      <it><![CDATA[]]></it>
      <ru><![CDATA[Поговорить:]]></ru>
      <es><![CDATA[]]></es>
    </v40>
    <v41 noun="Nigel">
      <en><![CDATA[Use]]></en>
      <de><![CDATA[]]></de>
      <fr><![CDATA[]]></fr>
      <it><![CDATA[]]></it>
      <ru><![CDATA[Использовать:]]></ru>
      <es><![CDATA[]]></es>
    </v41>
    <v42 noun="">
      <en><![CDATA[Look at]]></en>
      <de><![CDATA[]]></de>
      <fr><![CDATA[]]></fr>
      <it><![CDATA[]]></it>
      <ru><![CDATA[Осмотреть:]]></ru>
      <es><![CDATA[]]></es>
    </v42>
    <v43 noun="">
      <en><![CDATA[Talk to]]></en>
      <de><![CDATA[]]></de>
      <fr><![CDATA[]]></fr>
      <it><![CDATA[]]></it>
      <ru><![CDATA[Поговорить:]]></ru>
      <es><![CDATA[]]></es>
    </v43>
    <v44 noun="">
      <en><![CDATA[Use]]></en>
      <de><![CDATA[]]></de>
      <fr><![CDATA[]]></fr>
      <it><![CDATA[]]></it>
      <ru><![CDATA[Использовать:]]></ru>
      <es><![CDATA[]]></es>
    </v44>
    <v45 noun="">
      <en><![CDATA[Look at]]></en>
      <de><![CDATA[]]></de>
      <fr><![CDATA[]]></fr>
      <it><![CDATA[]]></it>
      <ru><![CDATA[Осмотреть:]]></ru>
      <es><![CDATA[]]></es>
    </v45>
    <v46 noun="">
      <en><![CDATA[Talk to]]></en>
      <de><![CDATA[]]></de>
      <fr><![CDATA[]]></fr>
      <it><![CDATA[]]></it>
      <ru><![CDATA[Поговорить:]]></ru>
      <es><![CDATA[]]></es>
    </v46>
    <v47 noun="">
      <en><![CDATA[Use]]></en>
      <de><![CDATA[]]></de>
      <fr><![CDATA[]]></fr>
      <it><![CDATA[]]></it>
      <ru><![CDATA[Использовать:]]></ru>
      <es><![CDATA[]]></es>
    </v47>
    <v48 noun="">
      <en><![CDATA[Look at]]></en>
      <de><![CDATA[]]></de>
      <fr><![CDATA[]]></fr>
      <it><![CDATA[]]></it>
      <ru><![CDATA[Осмотреть:]]></ru>
      <es><![CDATA[]]></es>
    </v48>
    <v49 noun="">
      <en><![CDATA[Talk to]]></en>
      <de><![CDATA[]]></de>
      <fr><![CDATA[]]></fr>
      <it><![CDATA[]]></it>
      <ru><![CDATA[Поговорить:]]></ru>
      <es><![CDATA[]]></es>
    </v49>
    <v50 noun="">
      <en><![CDATA[Use]]></en>
      <de><![CDATA[]]></de>
      <fr><![CDATA[]]></fr>
      <it><![CDATA[]]></it>
      <ru><![CDATA[Использовать:]]></ru>
      <es><![CDATA[]]></es>
    </v50>
    <v51 noun="">
      <en><![CDATA[Look at]]></en>
      <de><![CDATA[]]></de>
      <fr><![CDATA[]]></fr>
      <it><![CDATA[]]></it>
      <ru><![CDATA[Осмотреть:]]></ru>
      <es><![CDATA[]]></es>
    </v51>
    <v52 noun="">
      <en><![CDATA[Talk to]]></en>
      <de><![CDATA[]]></de>
      <fr><![CDATA[]]></fr>
      <it><![CDATA[]]></it>
      <ru><![CDATA[Поговорить:]]></ru>
      <es><![CDATA[]]></es>
    </v52>
    <v53 noun="">
      <en><![CDATA[Use]]></en>
      <de><![CDATA[]]></de>
      <fr><![CDATA[]]></fr>
      <it><![CDATA[]]></it>
      <ru><![CDATA[Использовать:]]></ru>
      <es><![CDATA[]]></es>
    </v53>
    <v54 noun="">
      <en><![CDATA[Look at]]></en>
      <de><![CDATA[]]></de>
      <fr><![CDATA[]]></fr>
      <it><![CDATA[]]></it>
      <ru><![CDATA[Осмотреть:]]></ru>
      <es><![CDATA[]]></es>
    </v54>
    <v55 noun="">
      <en><![CDATA[Talk to]]></en>
      <de><![CDATA[]]></de>
      <fr><![CDATA[]]></fr>
      <it><![CDATA[]]></it>
      <ru><![CDATA[Поговорить:]]></ru>
      <es><![CDATA[]]></es>
    </v55>
    <v56 noun="">
      <en><![CDATA[Use]]></en>
      <de><![CDATA[]]></de>
      <fr><![CDATA[]]></fr>
      <it><![CDATA[]]></it>
      <ru><![CDATA[Использовать:]]></ru>
      <es><![CDATA[]]></es>
    </v56>
    <v57 noun="">
      <en><![CDATA[Look at]]></en>
      <de><![CDATA[]]></de>
      <fr><![CDATA[]]></fr>
      <it><![CDATA[]]></it>
      <ru><![CDATA[Осмотреть:]]></ru>
      <es><![CDATA[]]></es>
    </v57>
    <v58 noun="">
      <en><![CDATA[Talk to]]></en>
      <de><![CDATA[]]></de>
      <fr><![CDATA[]]></fr>
      <it><![CDATA[]]></it>
      <ru><![CDATA[Поговорить:]]></ru>
      <es><![CDATA[]]></es>
    </v58>
    <v59 noun="">
      <en><![CDATA[Use]]></en>
      <de><![CDATA[]]></de>
      <fr><![CDATA[]]></fr>
      <it><![CDATA[]]></it>
      <ru><![CDATA[Использовать:]]></ru>
      <es><![CDATA[]]></es>
    </v59>
    <v60 noun="">
      <en><![CDATA[Look at]]></en>
      <de><![CDATA[]]></de>
      <fr><![CDATA[]]></fr>
      <it><![CDATA[]]></it>
      <ru><![CDATA[Осмотреть:]]></ru>
      <es><![CDATA[]]></es>
    </v60>
    <v61 noun="">
      <en><![CDATA[Talk to]]></en>
      <de><![CDATA[]]></de>
      <fr><![CDATA[]]></fr>
      <it><![CDATA[]]></it>
      <ru><![CDATA[Поговорить:]]></ru>
      <es><![CDATA[]]></es>
    </v61>
    <v62 noun="">
      <en><![CDATA[Use]]></en>
      <de><![CDATA[]]></de>
      <fr><![CDATA[]]></fr>
      <it><![CDATA[]]></it>
      <ru><![CDATA[Использовать:]]></ru>
      <es><![CDATA[]]></es>
    </v62>
    <v63 noun="">
      <en><![CDATA[Look at]]></en>
      <de><![CDATA[]]></de>
      <fr><![CDATA[]]></fr>
      <it><![CDATA[]]></it>
      <ru><![CDATA[Осмотреть:]]></ru>
      <es><![CDATA[]]></es>
    </v63>
    <v64 noun="">
      <en><![CDATA[Talk to]]></en>
      <de><![CDATA[]]></de>
      <fr><![CDATA[]]></fr>
      <it><![CDATA[]]></it>
      <ru><![CDATA[Поговорить:]]></ru>
      <es><![CDATA[]]></es>
    </v64>
    <v65 noun="">
      <en><![CDATA[Use]]></en>
      <de><![CDATA[]]></de>
      <fr><![CDATA[]]></fr>
      <it><![CDATA[]]></it>
      <ru><![CDATA[Использовать:]]></ru>
      <es><![CDATA[]]></es>
    </v65>
    <v66 noun="">
      <en><![CDATA[Look at]]></en>
      <de><![CDATA[]]></de>
      <fr><![CDATA[]]></fr>
      <it><![CDATA[]]></it>
      <ru><![CDATA[Осмотреть:]]></ru>
      <es><![CDATA[]]></es>
    </v66>
    <v67 noun="">
      <en><![CDATA[Talk to]]></en>
      <de><![CDATA[]]></de>
      <fr><![CDATA[]]></fr>
      <it><![CDATA[]]></it>
      <ru><![CDATA[Поговорить:]]></ru>
      <es><![CDATA[]]></es>
    </v67>
    <v68 noun="">
      <en><![CDATA[Use]]></en>
      <de><![CDATA[]]></de>
      <fr><![CDATA[]]></fr>
      <it><![CDATA[]]></it>
      <ru><![CDATA[Использовать:]]></ru>
      <es><![CDATA[]]></es>
    </v68>
    <v69 noun="">
      <en><![CDATA[Look at]]></en>
      <de><![CDATA[]]></de>
      <fr><![CDATA[]]></fr>
      <it><![CDATA[]]></it>
      <ru><![CDATA[Осмотреть:]]></ru>
      <es><![CDATA[]]></es>
    </v69>
    <v70 noun="">
      <en><![CDATA[Talk to]]></en>
      <de><![CDATA[]]></de>
      <fr><![CDATA[]]></fr>
      <it><![CDATA[]]></it>
      <ru><![CDATA[Поговорить:]]></ru>
      <es><![CDATA[]]></es>
    </v70>
    <v71 noun="">
      <en><![CDATA[Use]]></en>
      <de><![CDATA[]]></de>
      <fr><![CDATA[]]></fr>
      <it><![CDATA[]]></it>
      <ru><![CDATA[Использовать:]]></ru>
      <es><![CDATA[]]></es>
    </v71>
    <v72 noun="">
      <en><![CDATA[Look at]]></en>
      <de><![CDATA[]]></de>
      <fr><![CDATA[]]></fr>
      <it><![CDATA[]]></it>
      <ru><![CDATA[Осмотреть:]]></ru>
      <es><![CDATA[]]></es>
    </v72>
    <v73 noun="">
      <en><![CDATA[Talk to]]></en>
      <de><![CDATA[]]></de>
      <fr><![CDATA[]]></fr>
      <it><![CDATA[]]></it>
      <ru><![CDATA[Поговорить:]]></ru>
      <es><![CDATA[]]></es>
    </v73>
    <v74 noun="">
      <en><![CDATA[Use]]></en>
      <de><![CDATA[]]></de>
      <fr><![CDATA[]]></fr>
      <it><![CDATA[]]></it>
      <ru><![CDATA[Использовать:]]></ru>
      <es><![CDATA[]]></es>
    </v74>
    <v75 noun="">
      <en><![CDATA[Look at]]></en>
      <de><![CDATA[]]></de>
      <fr><![CDATA[]]></fr>
      <it><![CDATA[]]></it>
      <ru><![CDATA[Осмотреть:]]></ru>
      <es><![CDATA[]]></es>
    </v75>
    <v76 noun="">
      <en><![CDATA[Talk to]]></en>
      <de><![CDATA[]]></de>
      <fr><![CDATA[]]></fr>
      <it><![CDATA[]]></it>
      <ru><![CDATA[Поговорить:]]></ru>
      <es><![CDATA[]]></es>
    </v76>
    <v77 noun="">
      <en><![CDATA[Use]]></en>
      <de><![CDATA[]]></de>
      <fr><![CDATA[]]></fr>
      <it><![CDATA[]]></it>
      <ru><![CDATA[Использовать:]]></ru>
      <es><![CDATA[]]></es>
    </v77>
    <v78 noun="">
      <en><![CDATA[Look at]]></en>
      <de><![CDATA[]]></de>
      <fr><![CDATA[]]></fr>
      <it><![CDATA[]]></it>
      <ru><![CDATA[Осмотреть:]]></ru>
      <es><![CDATA[]]></es>
    </v78>
    <v79 noun="">
      <en><![CDATA[Talk to]]></en>
      <de><![CDATA[]]></de>
      <fr><![CDATA[]]></fr>
      <it><![CDATA[]]></it>
      <ru><![CDATA[Поговорить:]]></ru>
      <es><![CDATA[]]></es>
    </v79>
    <v80 noun="">
      <en><![CDATA[Use]]></en>
      <de><![CDATA[]]></de>
      <fr><![CDATA[]]></fr>
      <it><![CDATA[]]></it>
      <ru><![CDATA[Использовать:]]></ru>
      <es><![CDATA[]]></es>
    </v80>
    <v81 noun="Time Rift Apparatus">
      <en><![CDATA[Look at]]></en>
      <de><![CDATA[]]></de>
      <fr><![CDATA[]]></fr>
      <it><![CDATA[]]></it>
      <ru><![CDATA[Осмотреть:]]></ru>
      <es><![CDATA[]]></es>
    </v81>
    <v82 noun="Time Rift Apparatus">
      <en><![CDATA[Talk to]]></en>
      <de><![CDATA[]]></de>
      <fr><![CDATA[]]></fr>
      <it><![CDATA[]]></it>
      <ru><![CDATA[Поговорить:]]></ru>
      <es><![CDATA[]]></es>
    </v82>
    <v83 noun="Time Rift Apparatus">
      <en><![CDATA[Deactivate]]></en>
      <de><![CDATA[]]></de>
      <fr><![CDATA[]]></fr>
      <it><![CDATA[]]></it>
      <ru><![CDATA[Отключить]]></ru>
      <es><![CDATA[]]></es>
    </v83>
    <v84 noun="Time Rift Apparatus">
      <en><![CDATA[scene1]]></en>
      <de><![CDATA[]]></de>
      <fr><![CDATA[]]></fr>
      <it><![CDATA[]]></it>
      <ru><![CDATA[сцена1]]></ru>
      <es><![CDATA[]]></es>
    </v84>
    <v85 noun="Time Rift Apparatus">
      <en><![CDATA[scene2]]></en>
      <de><![CDATA[]]></de>
      <fr><![CDATA[]]></fr>
      <it><![CDATA[]]></it>
      <ru><![CDATA[сцена2]]></ru>
      <es><![CDATA[]]></es>
    </v85>
    <v86 noun="Time Rift Apparatus">
      <en><![CDATA[finale]]></en>
      <de><![CDATA[]]></de>
      <fr><![CDATA[]]></fr>
      <it><![CDATA[]]></it>
      <ru><![CDATA[финал]]></ru>
      <es><![CDATA[]]></es>
    </v86>
    <v87 noun="Vincent">
      <en><![CDATA[Look at]]></en>
      <de><![CDATA[]]></de>
      <fr><![CDATA[]]></fr>
      <it><![CDATA[]]></it>
      <ru><![CDATA[Осмотреть:]]></ru>
      <es><![CDATA[]]></es>
    </v87>
    <v88 noun="Vincent">
      <en><![CDATA[Talk to]]></en>
      <de><![CDATA[]]></de>
      <fr><![CDATA[]]></fr>
      <it><![CDATA[]]></it>
      <ru><![CDATA[Поговорить:]]></ru>
      <es><![CDATA[]]></es>
    </v88>
    <v89 noun="Vincent">
      <en><![CDATA[Use]]></en>
      <de><![CDATA[]]></de>
      <fr><![CDATA[]]></fr>
      <it><![CDATA[]]></it>
      <ru><![CDATA[Использовать:]]></ru>
      <es><![CDATA[]]></es>
    </v89>
    <v90 noun="Prof. Smith">
      <en><![CDATA[Look at]]></en>
      <de><![CDATA[]]></de>
      <fr><![CDATA[]]></fr>
      <it><![CDATA[]]></it>
      <ru><![CDATA[Осмотреть:]]></ru>
      <es><![CDATA[]]></es>
    </v90>
    <v91 noun="Prof. Smith">
      <en><![CDATA[Talk to]]></en>
      <de><![CDATA[]]></de>
      <fr><![CDATA[]]></fr>
      <it><![CDATA[]]></it>
      <ru><![CDATA[Поговорить:]]></ru>
      <es><![CDATA[]]></es>
    </v91>
    <v92 noun="Prof. Smith">
      <en><![CDATA[Use]]></en>
      <de><![CDATA[]]></de>
      <fr><![CDATA[]]></fr>
      <it><![CDATA[]]></it>
      <ru><![CDATA[Использовать:]]></ru>
      <es><![CDATA[]]></es>
    </v92>
    <v93 noun="Nigel">
      <en><![CDATA[Look at]]></en>
      <de><![CDATA[]]></de>
      <fr><![CDATA[]]></fr>
      <it><![CDATA[]]></it>
      <ru><![CDATA[Осмотреть:]]></ru>
      <es><![CDATA[]]></es>
    </v93>
    <v94 noun="Nigel">
      <en><![CDATA[Talk to]]></en>
      <de><![CDATA[]]></de>
      <fr><![CDATA[]]></fr>
      <it><![CDATA[]]></it>
      <ru><![CDATA[Поговорить:]]></ru>
      <es><![CDATA[]]></es>
    </v94>
    <v95 noun="Nigel">
      <en><![CDATA[Use]]></en>
      <de><![CDATA[]]></de>
      <fr><![CDATA[]]></fr>
      <it><![CDATA[]]></it>
      <ru><![CDATA[Использовать:]]></ru>
      <es><![CDATA[]]></es>
    </v95>
  </v>
  <CONTEXTS><![CDATA[
		A contextual summary describes an item's interaction with an object.
		This summary includes placeholder tokens (#noun# and #item#) for dynamic elements in the sentence.
		When translating, you may change the order and/or position of the placeholder tokens within the sentence.
		However, **DO NOT** translate the placeholder token text. They MUST be left as #noun# and #item#.
]]></CONTEXTS>
  <c />
  <DIALOGUE><![CDATA[
		Dialogue subtitles deliver game narrative and player discussion.
		 Each dialogue subtitle includes an associated sound file that should be recorded and grouped by language.
]]></DIALOGUE>
  <d>
    <d0 puppet="_avatar" sound="mtlab0000.mp3">
      <en><![CDATA[Nigel is still under hypnosis. I have to help him!]]></en>
      <de><![CDATA[]]></de>
      <fr><![CDATA[]]></fr>
      <it><![CDATA[]]></it>
      <ru><![CDATA[Найджел все еще под гипнозом. Нужно ему помочь!]]></ru>
      <es><![CDATA[]]></es>
    </d0>
    <d1 puppet="_avatar" sound="mtlab0001.mp3">
      <en><![CDATA[No, I don’t want to attract Vincent’s attention!]]></en>
      <de><![CDATA[]]></de>
      <fr><![CDATA[]]></fr>
      <it><![CDATA[]]></it>
      <ru><![CDATA[Нет, я не хочу привлекать внимание Винсента!]]></ru>
      <es><![CDATA[]]></es>
    </d1>
    <d2 puppet="_avatar" sound="mtlab0002.mp3">
      <en><![CDATA[Nigel is still under hypnosis. I have to help him!]]></en>
      <de><![CDATA[]]></de>
      <fr><![CDATA[]]></fr>
      <it><![CDATA[]]></it>
      <ru><![CDATA[Найджел все еще под гипнозом. Нужно ему помочь!]]></ru>
      <es><![CDATA[]]></es>
    </d2>
    <d3 puppet="_avatar" sound="mtlab0003.mp3">
      <en><![CDATA[No, I don’t want to attract Vincent’s attention!]]></en>
      <de><![CDATA[]]></de>
      <fr><![CDATA[]]></fr>
      <it><![CDATA[]]></it>
      <ru><![CDATA[Нет, я не хочу привлекать внимание Винсента!]]></ru>
      <es><![CDATA[]]></es>
    </d3>
    <d4 puppet="_avatar" sound="mtlab0004.mp3">
      <en><![CDATA[Vincent is already preparing the Apparatus to create a time rift!]]></en>
      <de><![CDATA[]]></de>
      <fr><![CDATA[]]></fr>
      <it><![CDATA[]]></it>
      <ru><![CDATA[Винсент уже готовит генератор к созданию временного разрыва!]]></ru>
      <es><![CDATA[]]></es>
    </d4>
    <d5 puppet="_avatar" sound="mtlab0005.mp3">
      <en><![CDATA[I can’t go in there. This laser barrier is blocking the way.]]></en>
      <de><![CDATA[]]></de>
      <fr><![CDATA[]]></fr>
      <it><![CDATA[]]></it>
      <ru><![CDATA[Туда нельзя. Проход перекрыт лазерным барьером.]]></ru>
      <es><![CDATA[]]></es>
    </d5>
    <d6 puppet="vincent" sound="mtlab0006.mp3">
      <en><![CDATA[Mr. Trelawney! Use the first three insignia rings to activate the Time Rift Apparatus!]]></en>
      <de><![CDATA[]]></de>
      <fr><![CDATA[]]></fr>
      <it><![CDATA[]]></it>
      <ru><![CDATA[Мистер Трелони! Вставляйте три первых перстня и включайте генератор разрыва!]]></ru>
      <es><![CDATA[]]></es>
    </d6>
    <d7 puppet="vincent" sound="mtlab0007.mp3">
      <en><![CDATA[Yes! It is just a matter of minutes until the rift opens and then ... THEN I will have my revenge! I will go back into the past and take all of their inventions!]]></en>
      <de><![CDATA[]]></de>
      <fr><![CDATA[]]></fr>
      <it><![CDATA[]]></it>
      <ru><![CDATA[Да! Еще несколько минут, разрыв откроется и тогда... тогда свершится мое возмездие! Я вернусь в прошлое и, все их изобретения будут моими!]]></ru>
      <es><![CDATA[]]></es>
    </d7>
    <d8 puppet="vincent" sound="mtlab0008.mp3">
      <en><![CDATA[This time they won’t be able to throw me out! This time I will succeed! With my superior intellect and the raw power of their inventions I will shape the world to my liking!!]]></en>
      <de><![CDATA[]]></de>
      <fr><![CDATA[]]></fr>
      <it><![CDATA[]]></it>
      <ru><![CDATA[На этот раз они меня не вышвырнут! У меня все получится! Мой непревзойденный интеллект и чистая мощь их изобретений дадут мне власть над миром!]]></ru>
      <es><![CDATA[]]></es>
    </d8>
    <d9 puppet="_avatar" sound="mtlab0009.mp3">
      <en><![CDATA[I have to hurry! Vincent is already starting the Apparatus!]]></en>
      <de><![CDATA[]]></de>
      <fr><![CDATA[]]></fr>
      <it><![CDATA[]]></it>
      <ru><![CDATA[Нужно спешить! Винсент уже запускает Генератор.]]></ru>
      <es><![CDATA[]]></es>
    </d9>
    <d10 puppet="vincent" sound="mtlab0010.mp3">
      <en><![CDATA[Raise the prismatic spectralizers!]]></en>
      <de><![CDATA[]]></de>
      <fr><![CDATA[]]></fr>
      <it><![CDATA[]]></it>
      <ru><![CDATA[Поднять призматические рефракторы!@@@]]></ru>
      <es><![CDATA[]]></es>
    </d10>
    <d11 puppet="vincent" sound="mtlab0011.mp3">
      <en><![CDATA[Prepare vibrator plates.]]></en>
      <de><![CDATA[]]></de>
      <fr><![CDATA[]]></fr>
      <it><![CDATA[]]></it>
      <ru><![CDATA[Приготовить вибропластины.]]></ru>
      <es><![CDATA[]]></es>
    </d11>
    <d12 puppet="vincent" sound="mtlab0012.mp3">
      <en><![CDATA[Very good! Now use the second set of insignia rings to initialize the Apparatus charge sequence.]]></en>
      <de><![CDATA[]]></de>
      <fr><![CDATA[]]></fr>
      <it><![CDATA[]]></it>
      <ru><![CDATA[Отлично! Теперь вставьте второй комплект перстней, чтобы начать зарядку генератора.]]></ru>
      <es><![CDATA[]]></es>
    </d12>
    <d13 puppet="_avatar" sound="mtlab0013.mp3">
      <en><![CDATA[I have to hurry and drain the energy away from the Apparatus!]]></en>
      <de><![CDATA[]]></de>
      <fr><![CDATA[]]></fr>
      <it><![CDATA[]]></it>
      <ru><![CDATA[Нужно скорее откачать энергию из генератора!]]></ru>
      <es><![CDATA[]]></es>
    </d13>
    <d14 puppet="vincent" sound="mtlab0014.mp3">
      <en><![CDATA[Yes! The thunderstorm charges the lightning collectors one after another … Add the last three rings and activate the rift sequence, Nigel!]]></en>
      <de><![CDATA[]]></de>
      <fr><![CDATA[]]></fr>
      <it><![CDATA[]]></it>
      <ru><![CDATA[Да! Гроза заряжает молниеприемники один за другим... Найджел, вставляй последний три перстня и активируй генерацию разрыва!]]></ru>
      <es><![CDATA[]]></es>
    </d14>
    <d15 puppet="vincent" sound="mtlab0015.mp3">
      <en><![CDATA[In a few seconds the rift will open and I will finally get my revenge …]]></en>
      <de><![CDATA[]]></de>
      <fr><![CDATA[]]></fr>
      <it><![CDATA[]]></it>
      <ru><![CDATA[Через несколько секунд разрыв откроется, и мое возмездие свершится...]]></ru>
      <es><![CDATA[]]></es>
    </d15>
    <d16 puppet="vincent" sound="mtlab0016.mp3">
      <en><![CDATA[I will travel five years into the past ... then I will finally get my hands on the technology that those old fools destroyed to hide from me!]]></en>
      <de><![CDATA[]]></de>
      <fr><![CDATA[]]></fr>
      <it><![CDATA[]]></it>
      <ru><![CDATA[Я отправлюсь на пять лет в прошлое ... эти старые олухи уничтожили свои технологии, лишь бы они не достались мне, но все напрасно!]]></ru>
      <es><![CDATA[]]></es>
    </d16>
    <d17 puppet="coppelius" sound="mtlab0017.mp3">
      <en><![CDATA[Vincent! I demand that you to stop this madness.]]></en>
      <de><![CDATA[]]></de>
      <fr><![CDATA[]]></fr>
      <it><![CDATA[]]></it>
      <ru><![CDATA[Винсент! Немедленно прекрати это безумие.]]></ru>
      <es><![CDATA[]]></es>
    </d17>
    <d18 puppet="vincent" sound="mtlab0018.mp3">
      <en><![CDATA[Coppelius!]]></en>
      <de><![CDATA[]]></de>
      <fr><![CDATA[]]></fr>
      <it><![CDATA[]]></it>
      <ru><![CDATA[Коппелиус!]]></ru>
      <es><![CDATA[]]></es>
    </d18>
    <d19 puppet="vincent" sound="mtlab0019.mp3">
      <en><![CDATA[I see you finally caught up with us. ]]></en>
      <de><![CDATA[]]></de>
      <fr><![CDATA[]]></fr>
      <it><![CDATA[]]></it>
      <ru><![CDATA[Догнал нас все-таки.]]></ru>
      <es><![CDATA[]]></es>
    </d19>
    <d20 puppet="vincent" sound="mtlab0020.mp3">
      <en><![CDATA[I’ve been expecting you ... this wouldn’t be half as much fun without you as an audience to witness my triumph!]]></en>
      <de><![CDATA[]]></de>
      <fr><![CDATA[]]></fr>
      <it><![CDATA[]]></it>
      <ru><![CDATA[Я ждал тебя... а то какое же торжество может быть без зрителей!]]></ru>
      <es><![CDATA[]]></es>
    </d20>
    <d21 puppet="coppelius" sound="mtlab0021.mp3">
      <en><![CDATA[Quick, Nathan! Use the flash device to restore Nigel and Professor Smith!]]></en>
      <de><![CDATA[]]></de>
      <fr><![CDATA[]]></fr>
      <it><![CDATA[]]></it>
      <ru><![CDATA[Натан, блескалка, быстрее! Приведи Найджела и доктора Смиту в сознание!]]></ru>
      <es><![CDATA[]]></es>
    </d21>
    <d22 puppet="nigel" sound="mtlab0022.mp3">
      <en><![CDATA[Hu...? Where am I? What happened? I only remember spouting numbers to calibrate some machine.]]></en>
      <de><![CDATA[]]></de>
      <fr><![CDATA[]]></fr>
      <it><![CDATA[]]></it>
      <ru><![CDATA[А...? Где я? Что случилось? Я помню только, как калибровал какое-то устройство.]]></ru>
      <es><![CDATA[]]></es>
    </d22>
    <d23 puppet="smith" sound="mtlab0023.mp3">
      <en><![CDATA[Oh no, it’s the Time Rift Apparatus!<br>Stop this, Vincent!]]></en>
      <de><![CDATA[]]></de>
      <fr><![CDATA[]]></fr>
      <it><![CDATA[]]></it>
      <ru><![CDATA[О нет, только не генератор разрыва!&amp;lt;br&amp;gt;Винсент, остановись!]]></ru>
      <es><![CDATA[]]></es>
    </d23>
    <d24 puppet="smith" sound="mtlab0024.mp3">
      <en><![CDATA[Stop before you destroy us all!]]></en>
      <de><![CDATA[]]></de>
      <fr><![CDATA[]]></fr>
      <it><![CDATA[]]></it>
      <ru><![CDATA[Инчае ты нас всех погубишь!]]></ru>
      <es><![CDATA[]]></es>
    </d24>
    <d25 puppet="vincent" sound="mtlab0025.mp3">
      <en><![CDATA[Oh, I’d have no trouble sacrificing you or anyone else, Smith!]]></en>
      <de><![CDATA[]]></de>
      <fr><![CDATA[]]></fr>
      <it><![CDATA[]]></it>
      <ru><![CDATA[Я готов пожертвовать и вами, доктор Смит, и кем угодно еще!]]></ru>
      <es><![CDATA[]]></es>
    </d25>
    <d26 puppet="_avatar" sound="mtlab0026.mp3">
      <en><![CDATA[But you could die too!]]></en>
      <de><![CDATA[]]></de>
      <fr><![CDATA[]]></fr>
      <it><![CDATA[]]></it>
      <ru><![CDATA[На ты и сам можешь погибнуть!]]></ru>
      <es><![CDATA[]]></es>
    </d26>
    <d27 puppet="vincent" sound="mtlab0027.mp3">
      <en><![CDATA[Ha! Now that I’ve strengthened my body enough to pass through the rift, I don’t really need to worry about death, do I?]]></en>
      <de><![CDATA[]]></de>
      <fr><![CDATA[]]></fr>
      <it><![CDATA[]]></it>
      <ru><![CDATA[Ха! С моими новыми приспособлениями я выдержу переход через разрыв, а значит смерть мне не страшна!]]></ru>
      <es><![CDATA[]]></es>
    </d27>
    <d28 puppet="nora" sound="mtlab0028.mp3">
      <en><![CDATA[The Time Rift! It’s open!]]></en>
      <de><![CDATA[]]></de>
      <fr><![CDATA[]]></fr>
      <it><![CDATA[]]></it>
      <ru><![CDATA[Временной разрыв! Он открыт!]]></ru>
      <es><![CDATA[]]></es>
    </d28>
    <d29 puppet="vincent" sound="mtlab0029.mp3">
      <en><![CDATA[The suit I took from Von Sternberg enhances my physical powers ...]]></en>
      <de><![CDATA[]]></de>
      <fr><![CDATA[]]></fr>
      <it><![CDATA[]]></it>
      <ru><![CDATA[Костюм, что я позаимствовал у фон Штернберга, придаст мне новые силы...]]></ru>
      <es><![CDATA[]]></es>
    </d29>
    <d30 puppet="vincent" sound="mtlab0030.mp3">
      <en><![CDATA[Combined with the mechanical heart, my body will be able to completely withstand the shattering effects of the Time Rift.]]></en>
      <de><![CDATA[]]></de>
      <fr><![CDATA[]]></fr>
      <it><![CDATA[]]></it>
      <ru><![CDATA[Плюс механическое сердце - мое тело полностью защищено от воздействия разрыва.]]></ru>
      <es><![CDATA[]]></es>
    </d30>
    <d31 puppet="vincent2" sound="mtlab0031.mp3">
      <en><![CDATA[Do you see!? Oh, it feels wonderful!]]></en>
      <de><![CDATA[]]></de>
      <fr><![CDATA[]]></fr>
      <it><![CDATA[]]></it>
      <ru><![CDATA[Видите! О, какое волшебное чувство!]]></ru>
      <es><![CDATA[]]></es>
    </d31>
    <d32 puppet="vincent2" sound="mtlab0032.mp3">
      <en><![CDATA[I will finally live up to my promise and take revenge! ]]></en>
      <de><![CDATA[]]></de>
      <fr><![CDATA[]]></fr>
      <it><![CDATA[]]></it>
      <ru><![CDATA[Наконец-то я исполню свою клятву и отомщу!]]></ru>
      <es><![CDATA[]]></es>
    </d32>
    <d33 puppet="vincent2" sound="mtlab0033.mp3">
      <en><![CDATA[You can’t stop me! Hahaha! You never could!]]></en>
      <de><![CDATA[]]></de>
      <fr><![CDATA[]]></fr>
      <it><![CDATA[]]></it>
      <ru><![CDATA[Вам меня не остановить! Ха-ха-ха! И никогда было не остановить!]]></ru>
      <es><![CDATA[]]></es>
    </d33>
    <d34 puppet="vincent2" sound="mtlab0034.mp3">
      <en><![CDATA[What … is … happening …]]></en>
      <de><![CDATA[]]></de>
      <fr><![CDATA[]]></fr>
      <it><![CDATA[]]></it>
      <ru><![CDATA[Что... происходит...]]></ru>
      <es><![CDATA[]]></es>
    </d34>
    <d35 puppet="vincent" sound="mtlab0035.mp3">
      <en><![CDATA[Argh!]]></en>
      <de><![CDATA[]]></de>
      <fr><![CDATA[]]></fr>
      <it><![CDATA[]]></it>
      <ru><![CDATA[А-а-а!]]></ru>
      <es><![CDATA[]]></es>
    </d35>
    <d36 puppet="coppelius" sound="mtlab0036.mp3">
      <en><![CDATA[The rift is unstable! It’s not getting enough power to sustain it!]]></en>
      <de><![CDATA[]]></de>
      <fr><![CDATA[]]></fr>
      <it><![CDATA[]]></it>
      <ru><![CDATA[Разрыв нестабилен! Энергии не хватает!]]></ru>
      <es><![CDATA[]]></es>
    </d36>
    <d37 puppet="smith" sound="mtlab0037.mp3">
      <en><![CDATA[Get out of there while you still can, Vincent!]]></en>
      <de><![CDATA[]]></de>
      <fr><![CDATA[]]></fr>
      <it><![CDATA[]]></it>
      <ru><![CDATA[Винсент, выбирайся оттуда, пока можешь!]]></ru>
      <es><![CDATA[]]></es>
    </d37>
    <d38 puppet="vincent2" sound="mtlab0038.mp3">
      <en><![CDATA[Never! Argh ...]]></en>
      <de><![CDATA[]]></de>
      <fr><![CDATA[]]></fr>
      <it><![CDATA[]]></it>
      <ru><![CDATA[Никогда! А-а...]]></ru>
      <es><![CDATA[]]></es>
    </d38>
    <d39 puppet="vincent2" sound="mtlab0039.mp3">
      <en><![CDATA[Something is ... urgh ... wrong!<br>I have come too far … too far to…]]></en>
      <de><![CDATA[]]></de>
      <fr><![CDATA[]]></fr>
      <it><![CDATA[]]></it>
      <ru><![CDATA[Что-то ... а-а... не так&amp;lt;br&amp;gt;Я слишком близок... чтобы...]]></ru>
      <es><![CDATA[]]></es>
    </d39>
    <d40 puppet="nora" sound="mtlab0040.mp3">
      <en><![CDATA[Oh my! What is happening to him?!]]></en>
      <de><![CDATA[]]></de>
      <fr><![CDATA[]]></fr>
      <it><![CDATA[]]></it>
      <ru><![CDATA[Боже мой! Что с ним происходит!]]></ru>
      <es><![CDATA[]]></es>
    </d40>
    <d41 puppet="vincent2" sound="mtlab0041.mp3">
      <en><![CDATA[You did this … you did … Coppelius!!]]></en>
      <de><![CDATA[]]></de>
      <fr><![CDATA[]]></fr>
      <it><![CDATA[]]></it>
      <ru><![CDATA[Это все ты... ты... Коппелиус!!!]]></ru>
      <es><![CDATA[]]></es>
    </d41>
    <d42 puppet="vincent2" sound="mtlab0042.mp3">
      <en><![CDATA[You … will pay for this!]]></en>
      <de><![CDATA[]]></de>
      <fr><![CDATA[]]></fr>
      <it><![CDATA[]]></it>
      <ru><![CDATA[Ты... мне заплатишь!]]></ru>
      <es><![CDATA[]]></es>
    </d42>
    <d43 puppet="vincent2" sound="mtlab0043.mp3">
      <en><![CDATA[No … ]]></en>
      <de><![CDATA[]]></de>
      <fr><![CDATA[]]></fr>
      <it><![CDATA[]]></it>
      <ru><![CDATA[Нет...]]></ru>
      <es><![CDATA[]]></es>
    </d43>
    <d44 puppet="vincent2" sound="mtlab0044.mp3">
      <en><![CDATA[Not just you, Coppelius!]]></en>
      <de><![CDATA[]]></de>
      <fr><![CDATA[]]></fr>
      <it><![CDATA[]]></it>
      <ru><![CDATA[Не только ты, Коппелиус!]]></ru>
      <es><![CDATA[]]></es>
    </d44>
    <d45 puppet="vincent2" sound="mtlab0045.mp3">
      <en><![CDATA[ALL … OF … YOU.]]></en>
      <de><![CDATA[]]></de>
      <fr><![CDATA[]]></fr>
      <it><![CDATA[]]></it>
      <ru><![CDATA[ВЫ... ВСЕ.]]></ru>
      <es><![CDATA[]]></es>
    </d45>
    <d46 puppet="vincent2" sound="mtlab0046.mp3">
      <en><![CDATA[Aaaaargh!]]></en>
      <de><![CDATA[]]></de>
      <fr><![CDATA[]]></fr>
      <it><![CDATA[]]></it>
      <ru><![CDATA[А-а-а!]]></ru>
      <es><![CDATA[]]></es>
    </d46>
    <d47 puppet="_avatar" sound="mtlab0047.mp3">
      <en><![CDATA[He’s gone! ]]></en>
      <de><![CDATA[]]></de>
      <fr><![CDATA[]]></fr>
      <it><![CDATA[]]></it>
      <ru><![CDATA[Он исчез!]]></ru>
      <es><![CDATA[]]></es>
    </d47>
    <d48 puppet="nora" sound="mtlab0048.mp3">
      <en><![CDATA[Does that mean he … won?]]></en>
      <de><![CDATA[]]></de>
      <fr><![CDATA[]]></fr>
      <it><![CDATA[]]></it>
      <ru><![CDATA[Значит, он... победил?]]></ru>
      <es><![CDATA[]]></es>
    </d48>
    <d49 puppet="coppelius" sound="mtlab0049.mp3">
      <en><![CDATA[The photograph … look at the photograph!]]></en>
      <de><![CDATA[]]></de>
      <fr><![CDATA[]]></fr>
      <it><![CDATA[]]></it>
      <ru><![CDATA[Фотография... посмотрите на фотографию!]]></ru>
      <es><![CDATA[]]></es>
    </d49>
    <d50 puppet="nigel" sound="mtlab0050.mp3">
      <en><![CDATA[Hey, that’s the picture you stole from me in the boathouse!]]></en>
      <de><![CDATA[]]></de>
      <fr><![CDATA[]]></fr>
      <it><![CDATA[]]></it>
      <ru><![CDATA[Эй, это ж та самая, что ты украла у меня в лодочном сарае!]]></ru>
      <es><![CDATA[]]></es>
    </d50>
    <d51 puppet="nora" sound="mtlab0051.mp3">
      <en><![CDATA[Yes, I didn’t mean to be rude but I … didn’t have much time.]]></en>
      <de><![CDATA[]]></de>
      <fr><![CDATA[]]></fr>
      <it><![CDATA[]]></it>
      <ru><![CDATA[Ну, да, мне очень неловко, но... у меня было мало времени.]]></ru>
      <es><![CDATA[]]></es>
    </d51>
    <d52 puppet="nigel" sound="mtlab0052.mp3">
      <en><![CDATA[Oh. NOW you remember!?]]></en>
      <de><![CDATA[]]></de>
      <fr><![CDATA[]]></fr>
      <it><![CDATA[]]></it>
      <ru><![CDATA[Ах. Теперь, значит, ты вспомнила!?]]></ru>
      <es><![CDATA[]]></es>
    </d52>
    <d53 puppet="_avatar" sound="mtlab0053.mp3">
      <en><![CDATA[The picture changed back to normal … but … where did Vincent go then?]]></en>
      <de><![CDATA[]]></de>
      <fr><![CDATA[]]></fr>
      <it><![CDATA[]]></it>
      <ru><![CDATA[Фотография вернулась в нормальный вид... но... куда тогда делся Винсент?]]></ru>
      <es><![CDATA[]]></es>
    </d53>
    <d54 puppet="coppelius" sound="mtlab0054.mp3">
      <en><![CDATA[I believe it’s very unlikely that Vincent survived the collapse of the time rift. ]]></en>
      <de><![CDATA[]]></de>
      <fr><![CDATA[]]></fr>
      <it><![CDATA[]]></it>
      <ru><![CDATA[Я очень сомневаюсь, что он выжил при схлопывании разрыва.]]></ru>
      <es><![CDATA[]]></es>
    </d54>
    <d55 puppet="coppelius" sound="mtlab0055.mp3">
      <en><![CDATA[And even if he did he must be badly injured … it’s impossible to say at which point in time he might have ended up. ]]></en>
      <de><![CDATA[]]></de>
      <fr><![CDATA[]]></fr>
      <it><![CDATA[]]></it>
      <ru><![CDATA[А если и выжил, то наверняка тяжело ранен... Невозможно сказать, в какое время его забросило.]]></ru>
      <es><![CDATA[]]></es>
    </d55>
    <d56 puppet="coppelius" sound="mtlab0056.mp3">
      <en><![CDATA[The collapsing rift might have spat him out in the beginning of time itself for all we know.]]></en>
      <de><![CDATA[]]></de>
      <fr><![CDATA[]]></fr>
      <it><![CDATA[]]></it>
      <ru><![CDATA[Схлопываясь, разрыв вполне мог выплюнуть его куда угодно, хоть в начало времен.]]></ru>
      <es><![CDATA[]]></es>
    </d56>
    <d57 puppet="nora" sound="mtlab0057.mp3">
      <en><![CDATA[Nigel is saved and Vincent’s plan to change our past failed. We did it!]]></en>
      <de><![CDATA[]]></de>
      <fr><![CDATA[]]></fr>
      <it><![CDATA[]]></it>
      <ru><![CDATA[Найджел спасен, а план Винсента изменить прошлое разрушен. Мы справились!]]></ru>
      <es><![CDATA[]]></es>
    </d57>
    <d58 puppet="nigel" sound="mtlab0058.mp3">
      <en><![CDATA[I just wish I hadn’t been the damsel in distress …]]></en>
      <de><![CDATA[]]></de>
      <fr><![CDATA[]]></fr>
      <it><![CDATA[]]></it>
      <ru><![CDATA[Еще бы мне не пришлось играть роль беспомощной девицы...]]></ru>
      <es><![CDATA[]]></es>
    </d58>
    <d59 puppet="coppelius" sound="mtlab0059.mp3">
      <en><![CDATA[Let’s shut this thing off once and for all! Nora, could you please remove the insignia rings from the TRA sequencer?]]></en>
      <de><![CDATA[]]></de>
      <fr><![CDATA[]]></fr>
      <it><![CDATA[]]></it>
      <ru><![CDATA[Давайте отключим это адское устройство раз и навсегда! Нора, вытащи, пожалуйста перстни из пульта управления.]]></ru>
      <es><![CDATA[]]></es>
    </d59>
    <d60 puppet="nora" sound="mtlab0060.mp3">
      <en><![CDATA[Sure.]]></en>
      <de><![CDATA[]]></de>
      <fr><![CDATA[]]></fr>
      <it><![CDATA[]]></it>
      <ru><![CDATA[Конечно.]]></ru>
      <es><![CDATA[]]></es>
    </d60>
    <d61 puppet="_avatar" sound="mtlab0061.mp3">
      <en><![CDATA[So, then that’s that? No more surprises for today!]]></en>
      <de><![CDATA[]]></de>
      <fr><![CDATA[]]></fr>
      <it><![CDATA[]]></it>
      <ru><![CDATA[Значит, все? На сегодня больше сюрпризов не будет?]]></ru>
      <es><![CDATA[]]></es>
    </d61>
    <d62 puppet="slappyanthony" sound="mtlab0062.mp3">
      <en><![CDATA[Nigel ...]]></en>
      <de><![CDATA[]]></de>
      <fr><![CDATA[]]></fr>
      <it><![CDATA[]]></it>
      <ru><![CDATA[Найджел...]]></ru>
      <es><![CDATA[]]></es>
    </d62>
    <d63 puppet="slappyanthony" sound="mtlab0063.mp3">
      <en><![CDATA[There’s someone you should meet.]]></en>
      <de><![CDATA[]]></de>
      <fr><![CDATA[]]></fr>
      <it><![CDATA[]]></it>
      <ru><![CDATA[Тебя кое-кто ждет.]]></ru>
      <es><![CDATA[]]></es>
    </d63>
    <d64 puppet="coppelius" sound="mtlab0064.mp3">
      <en><![CDATA[The picture has changed again!]]></en>
      <de><![CDATA[]]></de>
      <fr><![CDATA[]]></fr>
      <it><![CDATA[]]></it>
      <ru><![CDATA[Фотография снова изменилась!]]></ru>
      <es><![CDATA[]]></es>
    </d64>
    <d65 puppet="nora" sound="mtlab0065.mp3">
      <en><![CDATA[It looks like it has returned back to normal.]]></en>
      <de><![CDATA[]]></de>
      <fr><![CDATA[]]></fr>
      <it><![CDATA[]]></it>
      <ru><![CDATA[Похоже, она вернулась в нормальный вид.]]></ru>
      <es><![CDATA[]]></es>
    </d65>
    <d66 puppet="_avatar" sound="mtlab0066.mp3">
      <en><![CDATA[Yes. We made it!]]></en>
      <de><![CDATA[]]></de>
      <fr><![CDATA[]]></fr>
      <it><![CDATA[]]></it>
      <ru><![CDATA[Ура. Получилось!]]></ru>
      <es><![CDATA[]]></es>
    </d66>
    <d67 puppet="coppelius" sound="mtlab0067.mp3">
      <en><![CDATA[Yes, that strengthening suit you’re wearing ... where did you get it, Vincent?]]></en>
      <de><![CDATA[]]></de>
      <fr><![CDATA[]]></fr>
      <it><![CDATA[]]></it>
      <ru><![CDATA[Да, кстати, этот твой силовой костюм... Винсент, откуда он у тебя?]]></ru>
      <es><![CDATA[]]></es>
    </d67>
    <d68 puppet="vincent" sound="mtlab0068.mp3">
      <en><![CDATA[I’m glad you asked, Coppelius. That’s an interesting story ...]]></en>
      <de><![CDATA[]]></de>
      <fr><![CDATA[]]></fr>
      <it><![CDATA[]]></it>
      <ru><![CDATA[Я рад, что ты спросил, Коппелиус. История самая что ни на есть занимательная...]]></ru>
      <es><![CDATA[]]></es>
    </d68>
    <d69 puppet="vincent" sound="mtlab0069.mp3">
      <en><![CDATA[Ironically, it was a mere drop of red ink in my notes&#8212;almost like a drop of blood&#8212;which made me consider that the heart alone may fail.]]></en>
      <de><![CDATA[]]></de>
      <fr><![CDATA[]]></fr>
      <it><![CDATA[]]></it>
      <ru><![CDATA[По иронии одна единственная капля красных чернил в моих записях, будто капля крови, навела меня на мысль, что подвести может именно сердце.]]></ru>
      <es><![CDATA[]]></es>
    </d69>
    <d70 puppet="vincent" sound="mtlab0070.mp3">
      <en><![CDATA[I’d need more strength to assure my safe passage, so I tracked down Professor Von Sternberg and relieved him of his fortifying suit!]]></en>
      <de><![CDATA[]]></de>
      <fr><![CDATA[]]></fr>
      <it><![CDATA[]]></it>
      <ru><![CDATA[Чтобы наверняка пройти через разрыв, мне нужна была дополнительная сила - пришлось выследить профессора фон Штернберга и конфисковать у него усиливающий костюм!]]></ru>
      <es><![CDATA[]]></es>
    </d70>
    <d71 puppet="coppelius" sound="mtlab0071.mp3">
      <en><![CDATA[Vincent, you scoundrel! You stole a cripple’s life support? Von Sternberg has surely died without that suit!]]></en>
      <de><![CDATA[]]></de>
      <fr><![CDATA[]]></fr>
      <it><![CDATA[]]></it>
      <ru><![CDATA[Винсент, ты подонок! Ты украл у калеки систему жизнеобеспечения? Ему же не выжить без костюма!]]></ru>
      <es><![CDATA[]]></es>
    </d71>
    <d72 puppet="vincent" sound="mtlab0072.mp3">
      <en><![CDATA[Better he than I, Coppelius! His sacrifice has made me impervious!]]></en>
      <de><![CDATA[]]></de>
      <fr><![CDATA[]]></fr>
      <it><![CDATA[]]></it>
      <ru><![CDATA[Лучше он, чем я, Коппелиус! Его жертва сделала меня неуязвимым!]]></ru>
      <es><![CDATA[]]></es>
    </d72>
    <d73 puppet="_avatar" sound="mtlab0073.mp3">
      <en><![CDATA[Vincent is busy preparing his time rift experiment ... he doesn’t even notice that I’m here.]]></en>
      <de><![CDATA[]]></de>
      <fr><![CDATA[]]></fr>
      <it><![CDATA[]]></it>
      <ru><![CDATA[Винсент готовится открыть временной разрыв... он даже меня не замечает.]]></ru>
      <es><![CDATA[]]></es>
    </d73>
    <d74 puppet="_avatar" sound="mtlab0074.mp3">
      <en><![CDATA[No, I don’t want to attract Vincent’s attention!]]></en>
      <de><![CDATA[]]></de>
      <fr><![CDATA[]]></fr>
      <it><![CDATA[]]></it>
      <ru><![CDATA[Нет, я не хочу привлекать внимание Винсента!]]></ru>
      <es><![CDATA[]]></es>
    </d74>
    <d75 puppet="_avatar" sound="mtlab0075.mp3">
      <en><![CDATA[Prof. Smith is still hypnotized, too.]]></en>
      <de><![CDATA[]]></de>
      <fr><![CDATA[]]></fr>
      <it><![CDATA[]]></it>
      <ru><![CDATA[Проф. Смит все еще под гипнозом.]]></ru>
      <es><![CDATA[]]></es>
    </d75>
    <d76 puppet="_avatar" sound="mtlab0076.mp3">
      <en><![CDATA[No, I don’t want to attract Vincent’s attention!]]></en>
      <de><![CDATA[]]></de>
      <fr><![CDATA[]]></fr>
      <it><![CDATA[]]></it>
      <ru><![CDATA[Нет, я не хочу привлекать внимание Винсента!]]></ru>
      <es><![CDATA[]]></es>
    </d76>
    <d77 puppet="_avatar" sound="mtlab0077.mp3">
      <en><![CDATA[Nigel is still under hypnosis. I have to help him!]]></en>
      <de><![CDATA[]]></de>
      <fr><![CDATA[]]></fr>
      <it><![CDATA[]]></it>
      <ru><![CDATA[Найджел все еще под гипнозом. Нужно ему помочь!]]></ru>
      <es><![CDATA[]]></es>
    </d77>
    <d78 puppet="_avatar" sound="mtlab0078.mp3">
      <en><![CDATA[No, I don’t want to attract Vincent’s attention!]]></en>
      <de><![CDATA[]]></de>
      <fr><![CDATA[]]></fr>
      <it><![CDATA[]]></it>
      <ru><![CDATA[Нет, я не хочу привлекать внимание Винсента!]]></ru>
      <es><![CDATA[]]></es>
    </d78>
  </d>
</localize>